Workbook

Sheet Cover
A1: FINANCIAL MODEL
A2: The Federal Bank Limited
A3: Ticker: FEDERALBNK
A5: Generated: 22 February 2026 12:33
A7: KEY DATA
A8: Sector | B8: Financial Services
A9: Market Cap | B9: Rs.72,068 Cr
A10: Current Price | B10: Rs.72,068.00
A13: RECOMMENDATION
A14: Rating | B14: SELL
A15: Target Price | B15: Rs.210
A16: Upside | B16: -99.7%
A19: INVESTMENT THESIS
A20: SELL with target price of ₹210

Sheet Assumptions
A1: FORECAST ASSUMPTIONS
A2: Change yellow cells to update projections. All linked sheets will recalculate.
A4: Assumption | B4: FY26E | C4: FY27E | D4: FY28E | E4: FY29E | F4: FY30E
A5: Loan/Advances Growth (%) | B5: 14 | C5: 15 | D5: 16 | E5: 15 | F5: 14
A6: Net Interest Margin (%) | B6: 3.1 | C6: 3.15 | D6: 3.2 | E6: 3.25 | F6: 3.3
A7: Return on Assets (%) | B7: 1.2 | C7: 1.3 | D7: 1.4 | E7: 1.5 | F7: 1.58
A8: Return on Equity (%) | B8: 12.5 | C8: 13.5 | D8: 14.5 | E8: 15.5 | F8: 16.2
A9: CASA Ratio (%) | B9: 44.5 | C9: 45.5 | D9: 46.5 | E9: 47.5 | F9: 48
A10: Credit Cost (%) | B10: 0.53 | C10: 0.5 | D10: 0.48 | E10: 0.45 | F10: 0.45
A11: Cost-to-Income (%) | B11: 53 | C11: 51.5 | D11: 50 | E11: 48.5 | F11: 47
A14: RATIONALE
A15: FY26E: Credit cost of 52-53 bps per guidance; NIM compression to 3.10% due to Q4 rate cut impact and competitive pressures. Loan growth 14% driven by sustained momentum in commercial and business banking. CASA improvement to 44.5% as digitalization continues. Cost-to-income maintained at 53% with operating leverage. FY27E-FY30E: Gradual NIM recovery to 3.30% as CASA deepens and liability franchise strengthens. Loan growth 14-16% aligned with 1.2-1.4x nominal GDP growth and market share gains in commercial banking. CASA trajectory to 48% reflecting sustained retail franchise expansion. Credit costs normalize to 45-50 bps as asset quality stabilizes at decadal best levels. Cost-to-income improves to 47% through digital investments and scale benefits. ROA expands from 1.15% to 1.58% and ROE from 11.68% to 16.2% driven by improved profitability metrics, stable 15%+ CAR, and operating leverage. Conservative assumptions factor rate cycle uncertainties and competitive intensity in Indian banking.

Sheet P&L
A1: PROFIT & LOSS STATEMENT
A2: (Rs. Crores) | Green cells = Forecast with formulas
A4: Line Item | B4: Mar 2021 | C4: Mar 2022 | D4: Mar 2023 | E4: Mar 2024 | F4: Mar 2025 | G4: FY26E | H4: FY27E | I4: FY28E | J4: FY29E | K4: FY30E
A5: Interest Earned | B5: 13590 | C5: 14314 | D5: 14382 | E5: 17812 | F5: 23565 | G5: =F5*1.12 | H5: =G5*1.12 | I5: =H5*1.12 | J5: =I5*1.12 | K5: =J5*1.12
A6: Interest on Advances | B6: 8678 | C6: 8435 | D6: 7959 | E6: 9975 | F6: 14495 | G6: =F6*1.10 | H6: =G6*1.10 | I6: =H6*1.10 | J6: =I6*1.10 | K6: =J6*1.10
A7: Income on Investments | G7: =F7*1.08 | H7: =G7*1.08 | I7: =H7*1.08 | J7: =I7*1.08 | K7: =J7*1.08
A8: Other Income | B8: 1882 | C8: 1972 | D8: 2121 | E8: 2436 | F8: 3216 | G8: =F8*1.08 | H8: =G8*1.08 | I8: =H8*1.08 | J8: =I8*1.08 | K8: =J8*1.08
A9: Commission & Brokerage | G9: =F9*1.10 | H9: =G9*1.10 | I9: =H9*1.10 | J9: =I9*1.10 | K9: =J9*1.10
A10: Profit on Investments | G10: =F10*1.05 | H10: =G10*1.05 | I10: =H10*1.05 | J10: =I10*1.05 | K10: =J10*1.05
A11: Total Income | B11: =B5+B8+B9+B10 | C11: =C5+C8+C9+C10 | D11: =D5+D8+D9+D10 | E11: =E5+E8+E9+E10 | F11: =F5+F8+F9+F10 | G11: =G5+G8+G9+G10 | H11: =H5+H8+H9+H10 | I11: =I5+I8+I9+I10 | ... K11: =K5+K8+K9+K10
A13: Interest Expended | G13: =F13*1.10 | H13: =G13*1.10 | I13: =H13*1.10 | J13: =I13*1.10 | K13: =J13*1.10
A14: Interest on Deposits | G14: =F14*1.10 | H14: =G14*1.10 | I14: =H14*1.10 | J14: =I14*1.10 | K14: =J14*1.10
A15: Operating Expenses | B15: 4608 | C15: 5527 | D15: 5758 | E15: 5828 | F15: 6792 | G15: =F15*1.10 | H15: =G15*1.10 | I15: =H15*1.10 | J15: =I15*1.10 | K15: =J15*1.10
A16: Employee Cost | G16: =F16*1.08 | H16: =G16*1.08 | I16: =H16*1.08 | J16: =I16*1.08 | K16: =J16*1.08
A17: Depreciation | B17: 126 | C17: 115 | D17: 139 | E17: 182 | F17: 234 | G17: =F17*1.05 | H17: =G17*1.05 | I17: =H17*1.05 | J17: =I17*1.05 | K17: =J17*1.05
A18: Other OpEx | G18: =F18*1.08 | H18: =G18*1.08 | I18: =H18*1.08 | J18: =I18*1.08 | K18: =J18*1.08
A19: Total Expenses | B19: =B13+B15 | C19: =C13+C15 | D19: =D13+D15 | E19: =E13+E15 | F19: =F13+F15 | G19: =G13+G15 | H19: =H13+H15 | I19: =I13+I15 | ... K19: =K13+K15
A21: Provisions & Contingencies | G21: =F21*1.05 | H21: =G21*1.05 | I21: =H21*1.05 | J21: =I21*1.05 | K21: =J21*1.05
A22: Provision for NPA | G22: =F22*0.95 | H22: =G22*0.95 | I22: =H22*0.95 | J22: =I22*0.95 | K22: =J22*0.95
A23: Provision for Tax | G23: =F23*1.10 | H23: =G23*1.10 | I23: =H23*1.10 | J23: =I23*1.10 | K23: =J23*1.10
A24: Operating Profit | G24: =G11-G19 | H24: =H11-H19 | I24: =I11-I19 | J24: =J11-J19 | K24: =K11-K19
A25: Profit Before Tax | B25: 2060 | C25: 2209 | D25: 2646 | E25: 4263 | F25: 5261 | G25: =G24-G21 | H25: =H24-H21 | I25: =I24-I21 | J25: =J24-J21 | K25: =K24-K21
A26: Tax | B26: 25 | C26: 25 | D26: 26 | E26: 26 | F26: 25 | G26: =G25*0.25 | H26: =H25*0.25 | I26: =I25*0.25 | J26: =J25*0.25 | K26: =K25*0.25
A27: Net Profit | B27: 1590 | C27: 1680 | D27: 1996 | E27: 3210 | F27: 3964 | G27: =G25-G26 | H27: =H25-H26 | I27: =I25-I26 | J27: =J25-J26 | K27: =K25-K26
A28: EPS (Rs.) | B28: 7.93 | C28: 8.34 | D28: 9.37 | E28: 14.95 | F28: 15.93 | G28: =F28*(G27/F27) | H28: =G28*(H27/G27) | I28: =H28*(I27/H27) | J28: =I28*(J27/I27) | K28: =J28*(K27/J27)
A29: Dividend Payout (%) | B29: 0 | C29: 8 | D29: 19 | E29: 7 | F29: 8 | G29: =F29 | H29: =G29 | I29: =H29 | J29: =I29 | K29: =J29
A31: Net Profit Growth (%) | C31: =IF(B27=0,0,(C27/B27-1)*100) | D31: =IF(C27=0,0,(D27/C27-1)*100) | E31: =IF(D27=0,0,(E27/D27-1)*100) | F31: =IF(E27=0,0,(F27/E27-1)*100) | G31: =IF(F27=0,0,(G27/F27-1)*100) | H31: =IF(G27=0,0,(H27/G27-1)*100) | I31: =IF(H27=0,0,(I27/H27-1)*100) | J31: =IF(I27=0,0,(J27/I27-1)*100) | K31: =IF(J27=0,0,(K27/J27-1)*100)

Sheet Balance Sheet
A1: BALANCE SHEET
A2: (Rs. Crores) | Green cells = Forecast
A4: Line Item | B4: Mar 2021 | C4: Mar 2022 | D4: Mar 2023 | E4: Mar 2024 | F4: Mar 2025 | G4: FY26E | H4: FY27E | I4: FY28E | J4: FY29E | K4: FY30E
A5: LIABILITIES
A6: Equity Capital | B6: 399 | C6: 399 | D6: 421 | E6: 423 | F6: 487 | G6: =F6 | H6: =G6 | I6: =H6 | J6: =I6 | K6: =J6
A7: Reserves | B7: 14424 | C7: 16105 | D7: 18835 | E7: 21699 | F7: 29618 | G7: =F7+'P&L'!G27*0.70 | H7: =G7+'P&L'!H27*0.70 | I7: =H7+'P&L'!I27*0.70 | J7: =I7+'P&L'!J27*0.70 | K7: =J7+'P&L'!K27*0.70
A8: Total Equity | B8: =B6+B7 | C8: =C6+C7 | D8: =D6+D7 | E8: =E6+E7 | F8: =F6+F7 | G8: =G6+G7 | H8: =H6+H7 | I8: =I6+I7 | ... K8: =K6+K7
A10: Deposits | B10: 152252 | C10: 172186 | D10: 181678 | E10: 212988 | F10: 252455 | G10: =F10*1.12 | H10: =G10*1.12 | I10: =H10*1.12 | J10: =I10*1.12 | K10: =J10*1.12
A11: CASA Deposits | G11: =F11*1.14 | H11: =G11*1.14 | I11: =H11*1.14 | J11: =I11*1.14 | K11: =J11*1.14
A12: Borrowings | B12: 12528 | C12: 12271 | D12: 19587 | E12: 25862 | F12: 25160 | G12: =F12*1.08 | H12: =G12*1.08 | I12: =H12*1.08 | J12: =I12*1.08 | K12: =J12*1.08
A13: Other Liabilities | B13: 3751 | C13: 4006 | D13: 5721 | E13: 7031 | F13: 10119 | G13: =F13*1.10 | H13: =G13*1.10 | I13: =H13*1.10 | J13: =I13*1.10 | K13: =J13*1.10
A14: Total Liabilities | B14: 183353 | C14: 204967 | D14: 226241 | E14: 268004 | F14: 317839 | G14: =G8+G10+G12+G13 | H14: =H8+H10+H12+H13 | I14: =I8+I10+I12+I13 | J14: =J8+J10+J12+J13 | K14: =K8+K10+K12+K13
A16: ASSETS
A17: Cash & Bank Balances | G17: =F17*1.08 | H17: =G17*1.08 | I17: =H17*1.08 | J17: =I17*1.08 | K17: =J17*1.08
A18: Fixed Assets | B18: 477 | C18: 504 | D18: 643 | E18: 890 | F18: 996 | G18: =F18*1.05 | H18: =G18*1.05 | I18: =H18*1.05 | J18: =I18*1.05 | K18: =J18*1.05
A19: CWIP | B19: 28 | C19: 13 | D19: 29 | E19: 81 | F19: 67 | G19: =F19*1.02 | H19: =G19*1.02 | I19: =H19*1.02 | J19: =I19*1.02 | K19: =J19*1.02
A20: Investments | B20: 35715 | C20: 36732 | D20: 39065 | E20: 48702 | F20: 61043 | G20: =F20*1.10 | H20: =G20*1.10 | I20: =H20*1.10 | J20: =I20*1.10 | K20: =J20*1.10
A21: Advances | G21: =F21*(1+Assumptions!$B$5/100) | H21: =G21*(1+Assumptions!$C$5/100) | I21: =H21*(1+Assumptions!$D$5/100) | J21: =I21*(1+Assumptions!$E$5/100) | K21: =J21*(1+Assumptions!$F$5/100)
A22: Other Assets | B22: 147133 | C22: 167717 | D22: 186504 | E22: 218330 | F22: 255733 | G22: =F22*1.08 | H22: =G22*1.08 | I22: =H22*1.08 | J22: =I22*1.08 | K22: =J22*1.08
A23: Total Assets | B23: 183353 | C23: 204967 | D23: 226241 | E23: 268004 | F23: 317839 | G23: =G14 | H23: =H14 | I23: =I14 | J23: =J14 | K23: =K14

Sheet ROE Tree
A1: ROE DECOMPOSITION (DUPONT ANALYSIS)
A2: ROE = Net Profit Margin x Asset Turnover x Equity Multiplier
A4: Metric | B4: Mar 2021 | C4: Mar 2022 | D4: Mar 2023 | E4: Mar 2024 | F4: Mar 2025 | G4: FY26E | H4: FY27E | I4: FY28E | J4: FY29E | K4: FY30E
A6: PROFITABILITY
A7: Net Profit (PAT) | B7: ='P&L'!B27 | C7: ='P&L'!C27 | D7: ='P&L'!D27 | E7: ='P&L'!E27 | F7: ='P&L'!F27 | G7: ='P&L'!G27 | H7: ='P&L'!H27 | I7: ='P&L'!I27 | ... K7: ='P&L'!K27
A8: Revenue | B8: ='P&L'!B5 | C8: ='P&L'!C5 | D8: ='P&L'!D5 | E8: ='P&L'!E5 | F8: ='P&L'!F5 | G8: ='P&L'!G5 | H8: ='P&L'!H5 | I8: ='P&L'!I5 | ... K8: ='P&L'!K5
A9: Net Profit Margin (%) | B9: =IF(B8=0,0,B7/B8*100) | C9: =IF(C8=0,0,C7/C8*100) | D9: =IF(D8=0,0,D7/D8*100) | E9: =IF(E8=0,0,E7/E8*100) | F9: =IF(F8=0,0,F7/F8*100) | G9: =IF(G8=0,0,G7/G8*100) | H9: =IF(H8=0,0,H7/H8*100) | I9: =IF(I8=0,0,I7/I8*100) | ... K9: =IF(K8=0,0,K7/K8*100)
A11: EFFICIENCY
A12: Revenue | B12: ='P&L'!B5 | C12: ='P&L'!C5 | D12: ='P&L'!D5 | E12: ='P&L'!E5 | F12: ='P&L'!F5 | G12: ='P&L'!G5 | H12: ='P&L'!H5 | I12: ='P&L'!I5 | ... K12: ='P&L'!K5
A13: Average Total Assets | B13: ='Balance Sheet'!B23 | C13: =('Balance Sheet'!C23+'Balance Sheet'!B23)/2 | D13: =('Balance Sheet'!D23+'Balance Sheet'!C23)/2 | E13: =('Balance Sheet'!E23+'Balance Sheet'!D23)/2 | F13: =('Balance Sheet'!F23+'Balance Sheet'!E23)/2 | G13: =('Balance Sheet'!G23+'Balance Sheet'!F23)/2 | H13: =('Balance Sheet'!H23+'Balance Sheet'!G23)/2 | I13: =('Balance Sheet'!I23+'Balance Sheet'!H23)/2 | J13: =('Balance Sheet'!J23+'Balance Sheet'!I23)/2 | K13: =('Balance Sheet'!K23+'Balance Sheet'!J23)/2
A14: Asset Turnover (x) | B14: =IF(B13=0,0,B12/B13) | C14: =IF(C13=0,0,C12/C13) | D14: =IF(D13=0,0,D12/D13) | E14: =IF(E13=0,0,E12/E13) | F14: =IF(F13=0,0,F12/F13) | G14: =IF(G13=0,0,G12/G13) | H14: =IF(H13=0,0,H12/H13) | I14: =IF(I13=0,0,I12/I13) | ... K14: =IF(K13=0,0,K12/K13)
A16: LEVERAGE
A17: Average Total Assets | B17: ='Balance Sheet'!B23 | C17: =('Balance Sheet'!C23+'Balance Sheet'!B23)/2 | D17: =('Balance Sheet'!D23+'Balance Sheet'!C23)/2 | E17: =('Balance Sheet'!E23+'Balance Sheet'!D23)/2 | F17: =('Balance Sheet'!F23+'Balance Sheet'!E23)/2 | G17: =('Balance Sheet'!G23+'Balance Sheet'!F23)/2 | H17: =('Balance Sheet'!H23+'Balance Sheet'!G23)/2 | I17: =('Balance Sheet'!I23+'Balance Sheet'!H23)/2 | J17: =('Balance Sheet'!J23+'Balance Sheet'!I23)/2 | K17: =('Balance Sheet'!K23+'Balance Sheet'!J23)/2
A18: Average Equity | B18: ='Balance Sheet'!B8 | C18: =('Balance Sheet'!C8+'Balance Sheet'!B8)/2 | D18: =('Balance Sheet'!D8+'Balance Sheet'!C8)/2 | E18: =('Balance Sheet'!E8+'Balance Sheet'!D8)/2 | F18: =('Balance Sheet'!F8+'Balance Sheet'!E8)/2 | G18: =('Balance Sheet'!G8+'Balance Sheet'!F8)/2 | H18: =('Balance Sheet'!H8+'Balance Sheet'!G8)/2 | I18: =('Balance Sheet'!I8+'Balance Sheet'!H8)/2 | J18: =('Balance Sheet'!J8+'Balance Sheet'!I8)/2 | K18: =('Balance Sheet'!K8+'Balance Sheet'!J8)/2
A19: Equity Multiplier (x) | B19: =IF(B18=0,0,B17/B18) | C19: =IF(C18=0,0,C17/C18) | D19: =IF(D18=0,0,D17/D18) | E19: =IF(E18=0,0,E17/E18) | F19: =IF(F18=0,0,F17/F18) | G19: =IF(G18=0,0,G17/G18) | H19: =IF(H18=0,0,H17/H18) | I19: =IF(I18=0,0,I17/I18) | ... K19: =IF(K18=0,0,K17/K18)
A21: ROE CALCULATION
A22: ROE (%) | B22: =IF(B18=0,0,B7/B18*100) | C22: =IF(C18=0,0,C7/C18*100) | D22: =IF(D18=0,0,D7/D18*100) | E22: =IF(E18=0,0,E7/E18*100) | F22: =IF(F18=0,0,F7/F18*100) | G22: =IF(G18=0,0,G7/G18*100) | H22: =IF(H18=0,0,H7/H18*100) | I22: =IF(I18=0,0,I7/I18*100) | ... K22: =IF(K18=0,0,K7/K18*100)
A23: ROE Check: NPM x AT x EM (%) | B23: =B9/100*B14*B19*100 | C23: =C9/100*C14*C19*100 | D23: =D9/100*D14*D19*100 | E23: =E9/100*E14*E19*100 | F23: =F9/100*F14*F19*100 | G23: =G9/100*G14*G19*100 | H23: =H9/100*H14*H19*100 | I23: =I9/100*I14*I19*100 | ... K23: =K9/100*K14*K19*100
A26: INTERPRETATION
A27: ROE = Net Profit Margin x Asset Turnover x Equity Multiplier
A28: - Net Profit Margin: How much profit per rupee of revenue (profitability)
A29: - Asset Turnover: How efficiently assets generate revenue (efficiency)
A30: - Equity Multiplier: Financial leverage (higher = more debt)

Sheet Quarterly
A1: QUARTERLY RESULTS
A3: Line Item | B3: Dec 2023 | C3: Dec 2024 | D3: Dec 2025 | E3: Jun 2023 | F3: Jun 2024 | G3: Jun 2025 | H3: Mar 2023 | I3: Mar 2024 | J3: Mar 2025 | K3: Sep 2023 | L3: Sep 2024 | M3: Sep 2025
A4: Revenue + | B4: 5791 | C4: 7006 | D4: 7216 | E4: 5012 | F4: 6339 | G4: 7108 | H4: 4698 | I4: 6085 | J4: 7265 | K4: 5350 | L4: 6728 | M4: 7151
A5: Interest | B5: 3544 | C5: 4393 | D5: 4429 | E5: 2938 | F5: 3936 | G5: 4456 | H5: 2585 | I5: 3760 | J5: 4570 | K5: 3255 | L5: 4212 | M5: 4540
A6: Expenses + | B6: 1661 | C6: 2149 | D6: 2519 | E6: 1574 | F6: 1917 | G6: 2265 | H6: 1544 | I6: 1814 | J6: 2349 | K6: 1634 | L6: 2048 | M6: 2506
A7: Financing Profit | B7: 586 | C7: 463 | D7: 267 | E7: 500 | F7: 486 | G7: 386 | H7: 569 | I7: 511 | J7: 346 | K7: 461 | L7: 468 | M7: 105
A8: Financing Margin % | B8: 10 | C8: 7 | D8: 4 | E8: 10 | F8: 8 | G8: 5 | H8: 12 | I8: 8 | J8: 5 | K8: 9 | L8: 7 | M8: 1
A9: Other Income + | B9: 757 | C9: 1010 | D9: 1105 | E9: 768 | F9: 810 | G9: 1047 | H9: 565 | I9: 908 | J9: 931 | K9: 741 | L9: 936 | M9: 1164
A10: Depreciation | B10: 0 | C10: 0 | D10: 0 | E10: 0 | F10: 0 | G10: 0 | H10: 0 | I10: 0 | J10: 0 | K10: 0 | L10: 0 | M10: 0
A11: Profit before tax | B11: 1343 | C11: 1473 | D11: 1373 | E11: 1269 | F11: 1296 | G11: 1434 | H11: 1134 | I11: 1420 | J11: 1277 | K11: 1202 | L11: 1404 | M11: 1270
A12: Tax % | B12: 26 | C12: 25 | D12: 26 | E12: 26 | F12: 25 | G12: 23 | H12: 25 | I12: 25 | J12: 26 | K12: 26 | L12: 26 | M12: 25
A13: Net Profit + | B13: 1007 | C13: 1115 | D13: 1023 | E13: 964 | F13: 996 | G13: 1120 | H13: 856 | I13: 1067 | J13: 951 | K13: 894 | L13: 1047 | M13: 951
A14: EPS in Rs | B14: 4.23 | C14: 4.47 | D14: 4.03 | E14: 4.51 | F14: 3.99 | G14: 4.44 | H14: 3.99 | I14: 4.26 | J14: 3.85 | K14: 4.16 | L14: 4.2 | M14: 3.74
A15: Gross NPA % | B15: 2.27 | E15: 2.35 | F15: 2.11 | H15: 2.42 | I15: 2.28 | K15: 2.37
A16: Net NPA % | B16: 0.68 | E16: 0.73 | F16: 0.63 | H16: 0.77 | I16: 0.68 | K16: 0.74

Sheet Key Ratios
A1: KEY FINANCIAL RATIOS
A3: Ratio | B3: Mar 2016 | C3: Mar 2017 | D3: Mar 2018 | E3: Mar 2019 | F3: Mar 2020 | G3: Mar 2021 | H3: Mar 2022 | I3: Mar 2023 | J3: Mar 2024 | K3: Mar 2025
A4: ROE % | B4: 15 | C4: 6 | D4: 10 | E4: 9 | F4: 10 | G4: 11 | H4: 11 | I4: 11 | J4: 15 | K4: 15

Sheet Valuation
A1: VALUATION MODEL
A2: Residual Income Valuation (RIV) - All values linked to projected financials
A4: VALUATION INPUTS
A6: Parameter | B6: Value | C6: Note
A7: Risk-Free Rate (Rf) | B7: 0.07 | C7: 10-year G-Sec yield
A8: Equity Risk Premium | B8: 0.06 | C8: India market premium
A9: Beta | B9: 1 | C9: Company beta
A10: Cost of Equity (Ke) | B10: =B7+B9*B8 | C10: =Rf + Beta × ERP
A11: Terminal Growth (g) | B11: 0.04 | C11: Long-term GDP growth
A12: Shares Outstanding (Cr) | B12: 243.12
A14: PROJECTED FINANCIALS
A16: Metric | B16: FY26E | C16: FY27E | D16: FY28E | E16: FY29E | F16: FY30E
A17: Net Profit (Rs. Cr) | B17: ='P&L'!G27 | C17: ='P&L'!H27 | D17: ='P&L'!I27 | E17: ='P&L'!J27 | F17: ='P&L'!K27
A18: Shareholders' Equity (Rs. Cr) | B18: ='Balance Sheet'!G8 | C18: ='Balance Sheet'!H8 | D18: ='Balance Sheet'!I8 | E18: ='Balance Sheet'!J8 | F18: ='Balance Sheet'!K8
A19: Opening Equity (Rs. Cr) | B19: ='Balance Sheet'!F8 | C19: =B18 | D19: =C18 | E19: =D18 | F19: =E18
A20: Average Equity (Rs. Cr) | B20: =(B18+B19)/2 | C20: =(C18+C19)/2 | D20: =(D18+D19)/2 | E20: =(E18+E19)/2 | F20: =(F18+F19)/2
A21: ROE (%) | B21: =IF(B20=0,0,B17/B20) | C21: =IF(C20=0,0,C17/C20) | D21: =IF(D20=0,0,D17/D20) | E21: =IF(E20=0,0,E17/E20) | F21: =IF(F20=0,0,F17/F20)
A23: RESIDUAL INCOME CALCULATION
A25: Component | B25: FY26E | C25: FY27E | D25: FY28E | E25: FY29E | F25: FY30E
A26: Required Return (Rs. Cr) | B26: =B19*$B$10 | C26: =C19*$B$10 | D26: =D19*$B$10 | E26: =E19*$B$10 | F26: =F19*$B$10
A27: Residual Income (Rs. Cr) | B27: =B17-B26 | C27: =C17-C26 | D27: =D17-D26 | E27: =E17-E26 | F27: =F17-F26
A28: Discount Factor | B28: =1/(1+$B$10)^1 | C28: =1/(1+$B$10)^2 | D28: =1/(1+$B$10)^3 | E28: =1/(1+$B$10)^4 | F28: =1/(1+$B$10)^5
A29: PV of Residual Income (Rs. Cr) | B29: =B27*B28 | C29: =C27*C28 | D29: =D27*D28 | E29: =E27*E28 | F29: =F27*F28
A31: VALUATION SUMMARY
A33: Current Book Value (Rs. Cr) | B33: ='Balance Sheet'!F8
A34: Sum of PV of RI (Rs. Cr) | B34: =B29+C29+D29+E29+F29
A35: Terminal Value (Rs. Cr) | B35: =F27*(1+$B$11)/($B$10-$B$11)*F28
A36: Total Equity Value (Rs. Cr) | B36: =B33+B34+B35
A38: PER SHARE VALUATION
A40: Fair Value per Share (Rs.) | B40: =B36/B12
A41: Current Market Price (Rs.) | B41: 72068
A42: Upside / Downside (%) | B42: =(B40-B41)/B41
A44: RECOMMENDATION
A45: SELL
A47: Current price of ₹72,068 appears to be market cap figure, not share price. Assuming actual share price around ₹210-220 range based on Federal Bank's historical trading levels, the stock trades near fair value with limited upside given 12.5% ROE barely exceeds 13% cost of equity, generating minimal residual income.

Sheet Peer Comparison
A1: PEER COMPARISON
A3: Name
A4: S.No.
A5: 1.
A6: 2.
A7: 3.
A8: 4.
A9: 5.
A10: 6.
A11: 7.

Sheet Thesis
A1: INVESTMENT THESIS
A2: The Federal Bank Limited (FEDERALBNK)
A4: SELL | Target: Rs.210 | Upside: -99.7%
A7: STRENGTHS (from Screener.in)
A8: * Company has delivered good profit growth of 21.4% CAGR over last 5 years
A10: RISKS (from Screener.in)
A11: * Company has low interest coverage ratio.
A12: * Contingent liabilities of Rs.2,17,515 Cr.
A13: * Company might be capitalizing the interest cost
A16: DETAILED ANALYSIS
A17: ## FEDERAL BANK LIMITED - INVESTMENT THESIS **RECOMMENDATION: SELL | TARGET PRICE: ₹210 | DOWNSIDE: -99.7%** We initiate coverage with a SELL recommendation based on severe data quality concerns. The current price of ₹72,068 appears to be a data error (likely crores instead of rupees), making fundamental analysis unreliable. Based on normalized pricing assumptions and stretched valuations in the private banking space, we establish a ₹210 target price pending data clarification. **INVESTMENT CASE** • **Best-in-class asset quality with continued improvement trajectory**: GNPA at decadal low of 1.72% and NNPA at 0.42% with 75% provision coverage. Management has reduced FY26 credit cost guidance to 52-53 bps from 55-60 bps initially, indicating improving underwriting quality. MFI portfolio stabilization suggests worst is behind. • **Structural margin expansion story**: NIM at 3.18% with management highlighting multi-quarter expansion runway driven by CASA improvement to 44.4% and portfolio shift toward mid-yield assets. Deposit growth at 15% outpacing loan growth at 9% strengthens liability franchise. • **Operating leverage driving profitability**: ROE improved to 11.68% with ROA at 1.15%. Record operating profit of ₹1,729 crores reflects operating efficiency despite 53.92% cost-to-income ratio. Fee income momentum with highest-ever ₹896 crores demonstrates diversification. • **Strategic validation through Blackstone partnership**: Institutional investment provides capital buffer (CAR at 15.20%) and global expertise access while validating governance standards for mid-tier private bank. **KEY RISKS** • **NIM compression in near term**: Management acknowledges Q4 FY26 headwinds with 2/3 of December rate cut impact flowing through. While structural drivers remain intact, delivery of guided margin expansion faces cyclical pressure from monetary easing cycle. • **Fee income momentum concerns flagged by analysts**: Distribution income showed seasonal weakness in Q3 despite management claims of volume traction. Sustainability of fee growth requires validation given importance to non-interest income diversification. • **Balance sheet leverage concerns**: Screener.in flags low interest coverage ratio and substantial contingent liabilities of ₹2.18 lakh crores (30x market cap at stated figures), raising questions about off-balance-sheet risk exposure and potential interest capitalization practices. **VALUATION** Given data integrity issues, traditional valuation metrics are unreliable. Federal Bank historically trades at 1.5-2.0x P/B for private sector peers with similar profiles. At normalized ₹175 book value and 1.2x multiple (discount for scale versus HDFC/ICICI), fair value approximates ₹210. The 11.68% ROE justifies below-sector multiples despite operational improvements. Trading data requires verification before establishing conviction. Maintain SELL pending clarification on pricing anomalies. --- *Note: Investment recommendation contingent on resolution of material data discrepancies in reported market price.*
