Workbook

Sheet Cover
A1: FINANCIAL MODEL
A2: HDFC Bank Ltd
A3: Ticker: HDFCBANK
A5: Generated: 22 February 2026 12:01
A7: KEY DATA
A8: Sector | B8: Financial Services
A9: Market Cap | B9: Rs.1,322,419 Cr
A10: Current Price | B10: Rs.1,737.95
A13: RECOMMENDATION
A14: Rating | B14: HOLD
A15: Target Price | B15: Rs.1,820
A16: Upside | B16: 4.7%
A19: INVESTMENT THESIS
A20: HOLD with target price of ₹1820

Sheet Assumptions
A1: FORECAST ASSUMPTIONS
A2: Change yellow cells to update projections. All linked sheets will recalculate.
A4: Assumption | B4: FY26E | C4: FY27E | D4: FY28E | E4: FY29E | F4: FY30E
A5: Loan/Advances Growth (%) | B5: 11.9 | C5: 13.5 | D5: 14.5 | E5: 14 | F5: 13.5
A6: Net Interest Margin (%) | B6: 3.35 | C6: 3.4 | D6: 3.45 | E6: 3.5 | F6: 3.55
A7: Effective Tax Rate (%) | B7: 25 | C7: 25 | D7: 25 | E7: 25 | F7: 25
A8: Return on Assets (%) | B8: 1.92 | C8: 2 | D8: 2.08 | E8: 2.15 | F8: 2.2
A9: Return on Equity (%) | B9: 13.9 | C9: 14.5 | D9: 15 | E9: 15.5 | F9: 16
A10: CASA Ratio (%) | B10: 34 | C10: 35.5 | D10: 37 | E10: 38.5 | F10: 40
A11: Credit Cost (%) | B11: 0.45 | C11: 0.42 | D11: 0.4 | E11: 0.38 | F11: 0.35
A12: Cost-to-Income (%) | B12: 39.2 | C12: 38.5 | D12: 37.8 | E12: 37 | F12: 36.5
A15: RATIONALE
A16: HDFC Bank forecast reflects post-merger normalization with gradual CASA ratio recovery from current 34% toward historic 40%+ levels by FY30E. Loan growth normalizing at 12-14% range as integration effects stabilize. NIM expected to expand 15-20 bps over 5 years driven by CASA improvement and liability optimization. Asset quality remains strong with credit costs trending lower from current 45 bps to 35 bps reflecting excellent underwriting. Cost-to-income improving gradually through operating leverage and digital initiatives. ROA expanding from 1.92% to 2.20% and ROE from 13.9% to 16.0% as profitability metrics normalize post-merger. Strong capital base with CAR above regulatory requirements allows sustainable growth without dilution.

Sheet P&L
A1: PROFIT & LOSS STATEMENT
A2: (Rs. Crores) | Green cells = Forecast with formulas
A4: Line Item | B4: Mar 2021 | C4: Mar 2022 | D4: Mar 2023 | E4: Mar 2024 | F4: Mar 2025 | G4: FY26E | H4: FY27E | I4: FY28E | J4: FY29E | K4: FY30E
A5: Revenue / Interest Earned | B5: 122189 | C5: 128552 | D5: 135936 | E5: 170754 | F5: 283649 | G5: =F5*1.12 | H5: =G5*1.12 | I5: =H5*1.12 | J5: =I5*1.12 | K5: =J5*1.12
A6: Interest | B6: 62137 | C6: 59248 | D6: 58584 | E6: 77780 | F6: 154139 | G6: =F6*1.10 | H6: =G6*1.10 | I6: =H6*1.10 | J6: =I6*1.10 | K6: =J6*1.10
A7: Other Income | B7: 24879 | C7: 27333 | D7: 31759 | E7: 33912 | F7: 124346 | G7: =F7*1.08 | H7: =G7*1.08 | I7: =H7*1.08 | J7: =I7*1.08 | K7: =J7*1.08
A8: Total Income | B8: =B5+B6+B7 | C8: =C5+C6+C7 | D8: =D5+D6+D7 | E8: =E5+E6+E7 | F8: =F5+F6+F7 | G8: =G5+G6+G7 | H8: =H5+H6+H7 | I8: =I5+I6+I7 | ... K8: =K5+K6+K7
A10: Operating Expenses | B10: 45459 | C10: 52457 | D10: 56557 | E10: 63042 | F10: 174196 | G10: =F10*1.10 | H10: =G10*1.10 | I10: =H10*1.10 | J10: =I10*1.10 | K10: =J10*1.10
A11: Interest Expended | G11: =F11*1.08 | H11: =G11*1.08 | I11: =H11*1.08 | J11: =I11*1.08 | K11: =J11*1.08
A12: Depreciation | B12: 1277 | C12: 1385 | D12: 1681 | E12: 2345 | F12: 3092 | G12: =F12*1.05 | H12: =G12*1.05 | I12: =H12*1.05 | J12: =I12*1.05 | K12: =J12*1.05
A13: Provisions | G13: =F13*1.05 | H13: =G13*1.05 | I13: =H13*1.05 | J13: =I13*1.05 | K13: =J13*1.05
A14: Total Expenses | B14: =B10+B11+B12+B13 | C14: =C10+C11+C12+C13 | D14: =D10+D11+D12+D13 | E14: =E10+E11+E12+E13 | F14: =F10+F11+F12+F13 | G14: =G10+G11+G12+G13 | H14: =H10+H11+H12+H13 | I14: =I10+I11+I12+I13 | ... K14: =K10+K11+K12+K13
A16: Profit Before Tax | B16: 38195 | C16: 42796 | D16: 50873 | E16: 61498 | F16: 76569 | G16: =G8-G14 | H16: =H8-H14 | I16: =I8-I14 | J16: =J8-J14 | K16: =K8-K14
A17: Tax | B17: 29 | C17: 26 | D17: 25 | E17: 25 | F17: 15 | G17: =G16*Assumptions!$B$7/100 | H17: =H16*Assumptions!$C$7/100 | I17: =I16*Assumptions!$D$7/100 | J17: =J16*Assumptions!$E$7/100 | K17: =K16*Assumptions!$F$7/100
A18: Net Profit | B18: 27296 | C18: 31857 | D18: 38151 | E18: 46149 | F18: 65446 | G18: =G16-G17 | H18: =H16-H17 | I18: =I16-I17 | J18: =J16-J17 | K18: =K16-K17
A19: EPS (Rs.) | B19: 24.85 | C19: 28.87 | D19: 34.31 | E19: 41.22 | F19: 42.16 | G19: =F19*1.10 | H19: =G19*1.10 | I19: =H19*1.10 | J19: =I19*1.10 | K19: =J19*1.10
A21: Net Profit Growth (%) | C21: =IF(B18=0,0,(C18/B18-1)*100) | D21: =IF(C18=0,0,(D18/C18-1)*100) | E21: =IF(D18=0,0,(E18/D18-1)*100) | F21: =IF(E18=0,0,(F18/E18-1)*100) | G21: =IF(F18=0,0,(G18/F18-1)*100) | H21: =IF(G18=0,0,(H18/G18-1)*100) | I21: =IF(H18=0,0,(I18/H18-1)*100) | J21: =IF(I18=0,0,(J18/I18-1)*100) | K21: =IF(J18=0,0,(K18/J18-1)*100)

Sheet Balance Sheet
A1: BALANCE SHEET
A2: (Rs. Crores) | Green cells = Forecast
A4: Line Item | B4: Mar 2021 | C4: Mar 2022 | D4: Mar 2023 | E4: Mar 2024 | F4: Mar 2025 | G4: FY26E | H4: FY27E | I4: FY28E | J4: FY29E | K4: FY30E
A5: LIABILITIES
A6: Equity Capital | B6: 548 | C6: 551 | D6: 555 | E6: 558 | F6: 760 | G6: =F6 | H6: =G6 | I6: =H6 | J6: =I6 | K6: =J6
A7: Reserves | B7: 175810 | C7: 209259 | D7: 246772 | E7: 288880 | F7: 455636 | G7: =F7+'P&L'!G18*0.70 | H7: =G7+'P&L'!H18*0.70 | I7: =H7+'P&L'!I18*0.70 | J7: =I7+'P&L'!J18*0.70 | K7: =J7+'P&L'!K18*0.70
A8: Total Equity | B8: =B6+B7 | C8: =C6+C7 | D8: =D6+D7 | E8: =E6+E7 | F8: =F6+F7 | G8: =G6+G7 | H8: =H6+H7 | I8: =I6+I7 | ... K8: =K6+K7
A10: Deposits | B10: 1146207 | C10: 1333721 | D10: 1558003 | E10: 1882663 | F10: 2376887 | G10: =F10*1.12 | H10: =G10*1.12 | I10: =H10*1.12 | J10: =I10*1.12 | K10: =J10*1.12
A11: Borrowings | B11: 186834 | C11: 177697 | D11: 226966 | E11: 256549 | F11: 730615 | G11: =F11*1.08 | H11: =G11*1.08 | I11: =H11*1.08 | J11: =I11*1.08 | K11: =J11*1.08
A12: Other Liabilities | B12: 71430 | C12: 78279 | D12: 90639 | E12: 101783 | F12: 466296 | G12: =F12*1.10 | H12: =G12*1.10 | I12: =H12*1.10 | J12: =I12*1.10 | K12: =J12*1.10
A13: Total Liabilities | B13: 1580830 | C13: 1799507 | D13: 2122934 | E13: 2530432 | F13: 4030194 | G13: =G8+G10+G11+G12 | H13: =H8+H10+H11+H12 | I13: =I8+I10+I11+I12 | J13: =J8+J10+J11+J12 | K13: =K8+K10+K11+K12
A15: ASSETS
A16: Fixed Assets | B16: 4776 | C16: 5248 | D16: 6432 | E16: 8431 | F16: 12604 | G16: =F16*1.05 | H16: =G16*1.05 | I16: =H16*1.05 | J16: =I16*1.05 | K16: =J16*1.05
A17: CWIP | B17: 0 | C17: 0 | D17: 0 | E17: 0 | F17: 0 | G17: =F17*1.02 | H17: =G17*1.02 | I17: =H17*1.02 | J17: =I17*1.02 | K17: =J17*1.02
A18: Investments | B18: 389305 | C18: 438823 | D18: 449264 | E18: 511582 | F18: 1005682 | G18: =F18*1.10 | H18: =G18*1.10 | I18: =H18*1.10 | J18: =I18*1.10 | K18: =J18*1.10
A19: Advances | G19: =F19*(1+Assumptions!$B$5/100) | H19: =G19*(1+Assumptions!$C$5/100) | I19: =H19*(1+Assumptions!$D$5/100) | J19: =I19*(1+Assumptions!$E$5/100) | K19: =J19*(1+Assumptions!$F$5/100)
A20: Other Assets | B20: 1186750 | C20: 1355435 | D20: 1667238 | E20: 2010419 | F20: 3011909 | G20: =F20*1.08 | H20: =G20*1.08 | I20: =H20*1.08 | J20: =I20*1.08 | K20: =J20*1.08
A21: Total Assets | B21: 1580830 | C21: 1799507 | D21: 2122934 | E21: 2530432 | F21: 4030194 | G21: =G13 | H21: =H13 | I21: =I13 | J21: =J13 | K21: =K13

Sheet ROE Tree
A1: ROE DECOMPOSITION (DUPONT ANALYSIS)
A2: ROE = Net Profit Margin x Asset Turnover x Equity Multiplier
A4: Metric | B4: Mar 2021 | C4: Mar 2022 | D4: Mar 2023 | E4: Mar 2024 | F4: Mar 2025 | G4: FY26E | H4: FY27E | I4: FY28E | J4: FY29E | K4: FY30E
A6: PROFITABILITY
A7: Net Profit (PAT)
A8: Revenue
A9: Net Profit Margin (%) | B9: =IF(B8=0,0,B7/B8*100) | C9: =IF(C8=0,0,C7/C8*100) | D9: =IF(D8=0,0,D7/D8*100) | E9: =IF(E8=0,0,E7/E8*100) | F9: =IF(F8=0,0,F7/F8*100) | G9: =IF(G8=0,0,G7/G8*100) | H9: =IF(H8=0,0,H7/H8*100) | I9: =IF(I8=0,0,I7/I8*100) | ... K9: =IF(K8=0,0,K7/K8*100)
A11: EFFICIENCY
A12: Revenue
A13: Average Total Assets | B13: ='Balance Sheet'!B21 | C13: =('Balance Sheet'!C21+'Balance Sheet'!B21)/2 | D13: =('Balance Sheet'!D21+'Balance Sheet'!C21)/2 | E13: =('Balance Sheet'!E21+'Balance Sheet'!D21)/2 | F13: =('Balance Sheet'!F21+'Balance Sheet'!E21)/2 | G13: =('Balance Sheet'!G21+'Balance Sheet'!F21)/2 | H13: =('Balance Sheet'!H21+'Balance Sheet'!G21)/2 | I13: =('Balance Sheet'!I21+'Balance Sheet'!H21)/2 | J13: =('Balance Sheet'!J21+'Balance Sheet'!I21)/2 | K13: =('Balance Sheet'!K21+'Balance Sheet'!J21)/2
A14: Asset Turnover (x) | B14: =IF(B13=0,0,B12/B13) | C14: =IF(C13=0,0,C12/C13) | D14: =IF(D13=0,0,D12/D13) | E14: =IF(E13=0,0,E12/E13) | F14: =IF(F13=0,0,F12/F13) | G14: =IF(G13=0,0,G12/G13) | H14: =IF(H13=0,0,H12/H13) | I14: =IF(I13=0,0,I12/I13) | ... K14: =IF(K13=0,0,K12/K13)
A16: LEVERAGE
A17: Average Total Assets | B17: ='Balance Sheet'!B21 | C17: =('Balance Sheet'!C21+'Balance Sheet'!B21)/2 | D17: =('Balance Sheet'!D21+'Balance Sheet'!C21)/2 | E17: =('Balance Sheet'!E21+'Balance Sheet'!D21)/2 | F17: =('Balance Sheet'!F21+'Balance Sheet'!E21)/2 | G17: =('Balance Sheet'!G21+'Balance Sheet'!F21)/2 | H17: =('Balance Sheet'!H21+'Balance Sheet'!G21)/2 | I17: =('Balance Sheet'!I21+'Balance Sheet'!H21)/2 | J17: =('Balance Sheet'!J21+'Balance Sheet'!I21)/2 | K17: =('Balance Sheet'!K21+'Balance Sheet'!J21)/2
A18: Average Equity | B18: ='Balance Sheet'!B8 | C18: =('Balance Sheet'!C8+'Balance Sheet'!B8)/2 | D18: =('Balance Sheet'!D8+'Balance Sheet'!C8)/2 | E18: =('Balance Sheet'!E8+'Balance Sheet'!D8)/2 | F18: =('Balance Sheet'!F8+'Balance Sheet'!E8)/2 | G18: =('Balance Sheet'!G8+'Balance Sheet'!F8)/2 | H18: =('Balance Sheet'!H8+'Balance Sheet'!G8)/2 | I18: =('Balance Sheet'!I8+'Balance Sheet'!H8)/2 | J18: =('Balance Sheet'!J8+'Balance Sheet'!I8)/2 | K18: =('Balance Sheet'!K8+'Balance Sheet'!J8)/2
A19: Equity Multiplier (x) | B19: =IF(B18=0,0,B17/B18) | C19: =IF(C18=0,0,C17/C18) | D19: =IF(D18=0,0,D17/D18) | E19: =IF(E18=0,0,E17/E18) | F19: =IF(F18=0,0,F17/F18) | G19: =IF(G18=0,0,G17/G18) | H19: =IF(H18=0,0,H17/H18) | I19: =IF(I18=0,0,I17/I18) | ... K19: =IF(K18=0,0,K17/K18)
A21: ROE CALCULATION
A22: ROE (%) | B22: =IF(B18=0,0,B7/B18*100) | C22: =IF(C18=0,0,C7/C18*100) | D22: =IF(D18=0,0,D7/D18*100) | E22: =IF(E18=0,0,E7/E18*100) | F22: =IF(F18=0,0,F7/F18*100) | G22: =IF(G18=0,0,G7/G18*100) | H22: =IF(H18=0,0,H7/H18*100) | I22: =IF(I18=0,0,I7/I18*100) | ... K22: =IF(K18=0,0,K7/K18*100)
A23: ROE Check: NPM x AT x EM (%) | B23: =B9/100*B14*B19*100 | C23: =C9/100*C14*C19*100 | D23: =D9/100*D14*D19*100 | E23: =E9/100*E14*E19*100 | F23: =F9/100*F14*F19*100 | G23: =G9/100*G14*G19*100 | H23: =H9/100*H14*H19*100 | I23: =I9/100*I14*I19*100 | ... K23: =K9/100*K14*K19*100
A26: INTERPRETATION
A27: ROE = Net Profit Margin x Asset Turnover x Equity Multiplier
A28: - Net Profit Margin: How much profit per rupee of revenue (profitability)
A29: - Asset Turnover: How efficiently assets generate revenue (efficiency)
A30: - Equity Multiplier: Financial leverage (higher = more debt)

Sheet Quarterly
A1: QUARTERLY RESULTS
A3: Line Item | B3: Dec 2023 | C3: Dec 2024 | D3: Dec 2025 | E3: Jun 2023 | F3: Jun 2024 | G3: Jun 2025 | H3: Mar 2023 | I3: Mar 2024 | J3: Mar 2025 | K3: Sep 2023 | L3: Sep 2024 | M3: Sep 2025
A4: Revenue + | B4: 75039 | C4: 83002 | D4: 86994 | E4: 47548 | F4: 79434 | G4: 86779 | H4: 45002 | I4: 78008 | J4: 85040 | K4: 51168 | L4: 81546 | M4: 87372
A5: Interest | B5: 41250 | C5: 45414 | D5: 46741 | E5: 22606 | F5: 43692 | G5: 46986 | H5: 20505 | I5: 43242 | J5: 46914 | K5: 25955 | L5: 44580 | M5: 47709
A6: Expenses + | B6: 45349 | C6: 52074 | D6: 45161 | E6: 17770 | F6: 62938 | G6: 47709 | H6: 16682 | I6: 50530 | J6: 41307 | K6: 18470 | L6: 49690 | M6: 64497
A7: Financing Profit | B7: -11560 | C7: -14487 | D7: -4908 | E7: 7172 | F7: -27196 | G7: -7916 | H7: 7815 | I7: -15764 | J7: -3181 | K7: 6744 | L7: -12723 | M7: -24833
A8: Financing Margin % | B8: -15 | C8: -17 | D8: -6 | E8: 15 | F8: -34 | G8: -9 | H8: 17 | I8: -20 | J8: -4 | K8: 13 | L8: -16 | M8: -28
A9: Other Income + | B9: 32528 | C9: 38455 | D9: 31567 | E9: 9610 | F9: 44958 | G9: 33489 | H9: 9121 | I9: 37007 | J9: 27154 | K9: 9853 | L9: 35450 | M9: 45683
A10: Depreciation | B10: 0 | C10: 0 | D10: 0 | E10: 0 | F10: 0 | G10: 0 | H10: 0 | I10: 0 | J10: 0 | K10: 0 | L10: 0 | M10: 0
A11: Profit before tax | B11: 20967 | C11: 23968 | D11: 26659 | E11: 16783 | F11: 17761 | G11: 25573 | H11: 16936 | I11: 21243 | J11: 23973 | K11: 16597 | L11: 22727 | M11: 20850
A12: Tax % | B12: 17 | C12: 22 | D12: 24 | E12: 25 | F12: -1 | G12: 25 | H12: 25 | I12: 17 | J12: 24 | K12: 25 | L12: 24 | M12: 18
A13: Net Profit + | B13: 17312 | C13: 18627 | D13: 20364 | E13: 12634 | F13: 18013 | G13: 19285 | H13: 12735 | I13: 17718 | J13: 18340 | K13: 12403 | L13: 17188 | M13: 17090
A14: EPS in Rs | B14: 11.09 | C14: 11.68 | D14: 12.76 | E14: 11.29 | F14: 11.6 | G14: 12.31 | H14: 11.39 | I14: 11.37 | J14: 11.54 | K14: 11.06 | L14: 10.83 | M14: 10.6

Sheet Key Ratios
A1: KEY FINANCIAL RATIOS
A3: Ratio | B3: Mar 2016 | C3: Mar 2017 | D3: Mar 2018 | E3: Mar 2019 | F3: Mar 2020 | G3: Mar 2021 | H3: Mar 2022 | I3: Mar 2023 | J3: Mar 2024 | K3: Mar 2025
A4: ROE % | B4: 20 | C4: 19 | D4: 18 | E4: 18 | F4: 17 | G4: 16 | H4: 16 | I4: 17 | J4: 17 | K4: 17

Sheet Valuation
A1: VALUATION MODEL
A2: Residual Income Valuation (RIV) - All values linked to projected financials
A4: VALUATION INPUTS
A6: Parameter | B6: Value | C6: Note
A7: Risk-Free Rate (Rf) | B7: 0.07 | C7: 10-year G-Sec yield
A8: Equity Risk Premium | B8: 0.06 | C8: India market premium
A9: Beta | B9: 1 | C9: Company beta
A10: Cost of Equity (Ke) | B10: =B7+B9*B8 | C10: =Rf + Beta × ERP
A11: Terminal Growth (g) | B11: 0.04 | C11: Long-term GDP growth
A12: Shares Outstanding (Cr) | B12: 761.08
A14: PROJECTED FINANCIALS
A16: Metric | B16: FY26E | C16: FY27E | D16: FY28E | E16: FY29E | F16: FY30E
A17: Net Profit (Rs. Cr)
A18: Shareholders' Equity (Rs. Cr) | B18: ='Balance Sheet'!G8 | C18: ='Balance Sheet'!H8 | D18: ='Balance Sheet'!I8 | E18: ='Balance Sheet'!J8 | F18: ='Balance Sheet'!K8
A19: Opening Equity (Rs. Cr) | B19: ='Balance Sheet'!F8 | C19: =B18 | D19: =C18 | E19: =D18 | F19: =E18
A20: Average Equity (Rs. Cr) | B20: =(B18+B19)/2 | C20: =(C18+C19)/2 | D20: =(D18+D19)/2 | E20: =(E18+E19)/2 | F20: =(F18+F19)/2
A21: ROE (%) | B21: =IF(B20=0,0,B17/B20) | C21: =IF(C20=0,0,C17/C20) | D21: =IF(D20=0,0,D17/D20) | E21: =IF(E20=0,0,E17/E20) | F21: =IF(F20=0,0,F17/F20)
A23: RESIDUAL INCOME CALCULATION
A25: Component | B25: FY26E | C25: FY27E | D25: FY28E | E25: FY29E | F25: FY30E
A26: Required Return (Rs. Cr) | B26: =B19*$B$10 | C26: =C19*$B$10 | D26: =D19*$B$10 | E26: =E19*$B$10 | F26: =F19*$B$10
A27: Residual Income (Rs. Cr) | B27: =B17-B26 | C27: =C17-C26 | D27: =D17-D26 | E27: =E17-E26 | F27: =F17-F26
A28: Discount Factor | B28: =1/(1+$B$10)^1 | C28: =1/(1+$B$10)^2 | D28: =1/(1+$B$10)^3 | E28: =1/(1+$B$10)^4 | F28: =1/(1+$B$10)^5
A29: PV of Residual Income (Rs. Cr) | B29: =B27*B28 | C29: =C27*C28 | D29: =D27*D28 | E29: =E27*E28 | F29: =F27*F28
A31: VALUATION SUMMARY
A33: Current Book Value (Rs. Cr) | B33: ='Balance Sheet'!F8
A34: Sum of PV of RI (Rs. Cr) | B34: =B29+C29+D29+E29+F29
A35: Terminal Value (Rs. Cr) | B35: =F27*(1+$B$11)/($B$10-$B$11)*F28
A36: Total Equity Value (Rs. Cr) | B36: =B33+B34+B35
A38: PER SHARE VALUATION
A40: Fair Value per Share (Rs.) | B40: =B36/B12
A41: Current Market Price (Rs.) | B41: 1737.95
A42: Upside / Downside (%) | B42: =(B40-B41)/B41
A44: RECOMMENDATION
A45: HOLD
A47: ROE of 13.9% marginally exceeds cost of equity of 13%, generating modest residual income. Given limited spread and premium valuation typical of quality private banks, current price offers fair value with minimal upside.

Sheet Peer Comparison
A1: PEER COMPARISON
A3: Name
A4: S.No.
A5: 1.
A6: 2.
A7: 3.
A8: 4.
A9: 5.
A10: 6.
A11: 7.

Sheet Thesis
A1: INVESTMENT THESIS
A2: HDFC Bank Ltd (HDFCBANK)
A4: HOLD | Target: Rs.1,820 | Upside: 4.7%
A7: STRENGTHS (from Screener.in)
A8: * Company has delivered good profit growth of 21.0% CAGR over last 5 years
A9: * Company has been maintaining a healthy dividend payout of 23.3%
A10: * Company's median sales growth is 16.4% of last 10 years
A12: RISKS (from Screener.in)
A13: * Stock is trading at 2.50 times its book value
A14: * Company has low interest coverage ratio.
A15: * Contingent liabilities of Rs.27,80,601 Cr.
A16: * Earnings include an other income of Rs.1,50,600 Cr.
... A20: # HDFC Bank Ltd (HDFCBANK) - Investment Note ## RECOMMENDATION SUMMARY **HOLD** with target price of ₹1,820 (4.7% upside from current ₹1,737.95). Limited near-term upside following post-merger integration challenges, though franchise quality remains intact. ## INVESTMENT CASE • **Best-in-class asset quality with diversified portfolio**: GNPA at 1.24% (ex-agri: 0.97%) and NNPA at 0.40% with 70% provision coverage ratio demonstrates superior underwriting standards. Balanced retail mix (53% of AUM) across mortgage (30%) and retail assets (23%) provides portfolio stability. • **Sustained profitability and capital strength**: Strong 21% profit CAGR over five years with ROE at 13.9% and ROA at 1.92%. Fortress balance sheet with CAR at 19.9% and CET1 at 17.4% provides ample headroom for growth and shareholder returns (23.3% dividend payout). • **Operational efficiency leader**: Cost-to-income ratio of 39.2% remains among the best in private banking. NIM at 3.35% despite post-merger CASA pressure (34%) reflects pricing power and strong liability franchise with ₹3 trillion deposit growth (12.2% YoY). • **Consistent growth momentum**: Median sales growth of 16.4% over 10 years with current loan growth at 11.9% and deposit growth at 11.6% demonstrates ability to scale while maintaining quality through credit cycles. ## KEY RISKS • **CASA normalization pressuring margins**: CASA ratio at 34% remains below historical levels post-HDFC Ltd merger. Further compression could impact NIMs and profitability if rate cycle remains adverse or competition for deposits intensifies. • **Elevated contingent liabilities**: ₹27.8 lakh crore in contingent liabilities (primarily guarantees and derivatives) requires monitoring. Low interest coverage ratio suggests potential vulnerability to rate volatility. • **Valuation leaves limited margin of safety**: Trading at 2.50x book value with only 4.7% upside to target. Rich multiples vulnerable to derating if growth disappoints or asset quality deteriorates from current benign levels. ## VALUATION Target price of ₹1,820 implies 2.6x FY26E P/B, justified by superior ROE profile and franchise quality. However, current 2.50x book already prices in near-term growth prospects. Maintain HOLD given limited upside; initiate/add on pullback toward 2.0-2.2x book value where risk-reward becomes more attractive. Quality franchise warrants premium valuation, but await better entry point for fresh deployment. --- *Market Cap: ₹13.2 trillion | Sector: Financial Services*
