Workbook

Sheet Cover
A1: FINANCIAL MODEL
A2: HDFC Bank Ltd
A3: Ticker: HDFCBANK
A5: Generated: 22 February 2026 10:50
A7: KEY DATA
A8: Sector | B8: Financial Services
A9: Market Cap | B9: Rs.1,325,000 Cr
A10: Current Price | B10: Rs.1,742.85
A13: RECOMMENDATION
A14: Rating | B14: HOLD
A15: Target Price | B15: Rs.1,850
A16: Upside | B16: 6.1%
A19: INVESTMENT THESIS
A20: HOLD with target price of ₹1850

Sheet Assumptions
A1: FORECAST ASSUMPTIONS
A2: Change yellow cells to update projections. All linked sheets will recalculate.
A4: Assumption | B4: FY26E | C4: FY27E | D4: FY28E | E4: FY29E | F4: FY30E
A5: Loan/Advances Growth (%) | B5: 14 | C5: 14 | D5: 13 | E5: 13 | F5: 12
A6: Net Interest Margin (%) | B6: 4.1 | C6: 4 | D6: 3.9 | E6: 3.9 | F6: 3.8
A7: Return on Assets (%) | B7: 2 | C7: 2.1 | D7: 2.1 | E7: 2.2 | F7: 2.2
A8: Return on Equity (%) | B8: 16.5 | C8: 17 | D8: 17.5 | E8: 18 | F8: 18.5
A9: CASA Ratio (%) | B9: 43 | C9: 44 | D9: 45 | E9: 46 | F9: 47
A10: Credit Cost (%) | B10: 1.1 | C10: 1 | D10: 1 | E10: 0.9 | F10: 0.9
A11: Cost-to-Income (%) | B11: 41 | C11: 40 | D11: 39 | E11: 38 | F11: 38
A14: RATIONALE
A15: HDFC Bank post-merger is expected to maintain strong loan growth of 12-14% driven by India's economic growth and market share gains. NIM projected at 3.8-4.1%, slightly moderating from current levels due to competitive pressure but remaining among sector leaders. CASA ratio improvement from 43% to 47% as liability franchise strengthens post-integration. Credit costs normalize to 0.9-1.1% reflecting best-in-class underwriting. Cost-to-income improves to 38-41% through operating leverage and merger synergies. ROA of 2.0-2.2% and ROE of 16.5-18.5% positions HDFC Bank as sector leader in profitability metrics, supported by superior asset quality, liability franchise, and operational efficiency.

Sheet P&L
A1: PROFIT & LOSS STATEMENT
A2: (Rs. Crores) | Green cells = Forecast with formulas linked to Assumptions
A4: Line Item | B4: Mar 2021 | C4: Mar 2022 | D4: Mar 2023 | E4: Mar 2024 | F4: Mar 2025 | G4: FY26E | H4: FY27E | I4: FY28E | J4: FY29E | K4: FY30E
A5: Revenue + | B5: 122189 | C5: 128552 | D5: 135936 | E5: 170754 | F5: 283649 | G5: =F5*1.10 | H5: =G5*1.10 | I5: =H5*1.10 | J5: =I5*1.10 | K5: =J5*1.10
A6: Interest | B6: 62137 | C6: 59248 | D6: 58584 | E6: 77780 | F6: 154139 | G6: =F6*(1+Assumptions!$B$5/100) | H6: =G6*(1+Assumptions!$C$5/100) | I6: =H6*(1+Assumptions!$D$5/100) | J6: =I6*(1+Assumptions!$E$5/100) | K6: =J6*(1+Assumptions!$F$5/100)
A7: Other Income + | B7: 24879 | C7: 27333 | D7: 31759 | E7: 33912 | F7: 124346 | G7: =F7*1.05 | H7: =G7*1.05 | I7: =H7*1.05 | J7: =I7*1.05 | K7: =J7*1.05
A8: Total Income | G8: =G5+G6+G7 | H8: =H5+H6+H7 | I8: =I5+I6+I7 | J8: =J5+J6+J7 | K8: =K5+K6+K7
A10: Operating Expenses | B10: 45459 | C10: 52457 | D10: 56557 | E10: 63042 | F10: 174196 | G10: =F10*1.08 | H10: =G10*1.08 | I10: =H10*1.08 | J10: =I10*1.08 | K10: =J10*1.08
A11: Employee Cost | G11: =F11*1.08 | H11: =G11*1.08 | I11: =H11*1.08 | J11: =I11*1.08 | K11: =J11*1.08
A12: Interest Expense | B12: 62137 | C12: 59248 | D12: 58584 | E12: 77780 | F12: 154139 | G12: =F12*1.06 | H12: =G12*1.06 | I12: =H12*1.06 | J12: =I12*1.06 | K12: =J12*1.06
A13: Depreciation | B13: 1277 | C13: 1385 | D13: 1681 | E13: 2345 | F13: 3092 | G13: =F13*1.05 | H13: =G13*1.05 | I13: =H13*1.05 | J13: =I13*1.05 | K13: =J13*1.05
A14: Other Expenses | G14: =F14*1.07 | H14: =G14*1.07 | I14: =H14*1.07 | J14: =I14*1.07 | K14: =J14*1.07
A15: Total Expenses | G15: =G10+G11+G12+G13+G14 | H15: =H10+H11+H12+H13+H14 | I15: =I10+I11+I12+I13+I14 | J15: =J10+J11+J12+J13+J14 | K15: =K10+K11+K12+K13+K14
A17: Profit before tax | B17: 38195 | C17: 42796 | D17: 50873 | E17: 61498 | F17: 76569 | G17: =G8-G15 | H17: =H8-H15 | I17: =I8-I15 | J17: =J8-J15 | K17: =K8-K15
A18: Tax % | B18: 29 | C18: 26 | D18: 25 | E18: 25 | F18: 15 | G18: =G17*0.25 | H18: =H17*0.25 | I18: =I17*0.25 | J18: =J17*0.25 | K18: =K17*0.25
A19: Net Profit + | B19: 27296 | C19: 31857 | D19: 38151 | E19: 46149 | F19: 65446 | G19: =G17-G18 | H19: =H17-H18 | I19: =I17-I18 | J19: =J17-J18 | K19: =K17-K18
A21: PAT YoY Growth (%) | C21: =(C19/B19-1)*100 | D21: =(D19/C19-1)*100 | E21: =(E19/D19-1)*100 | F21: =(F19/E19-1)*100 | G21: =(G19/F19-1)*100 | H21: =(H19/G19-1)*100 | I21: =(I19/H19-1)*100 | J21: =(J19/I19-1)*100 | K21: =(K19/J19-1)*100

Sheet Balance Sheet
A1: BALANCE SHEET
A2: (Rs. Crores) | Green cells = Forecast
A4: Line Item | B4: Mar 2021 | C4: Mar 2022 | D4: Mar 2023 | E4: Mar 2024 | F4: Mar 2025 | G4: FY26E | H4: FY27E | I4: FY28E | J4: FY29E | K4: FY30E
A5: ASSETS
A6: Share Capital | G6: =F6 | H6: =G6 | I6: =H6 | J6: =I6 | K6: =J6
A7: Reserves | B7: 175810 | C7: 209259 | D7: 246772 | E7: 288880 | F7: 455636 | G7: =F7+'P&L'!G19*0.7 | H7: =G7+'P&L'!H19*0.7 | I7: =H7+'P&L'!I19*0.7 | J7: =I7+'P&L'!J19*0.7 | K7: =J7+'P&L'!K19*0.7
A8: Total Equity | G8: =G6+G7 | H8: =H6+H7 | I8: =I6+I7 | J8: =J6+J7 | K8: =K6+K7
A10: Borrowings | G10: =F10*1.08 | H10: =G10*1.08 | I10: =H10*1.08 | J10: =I10*1.08 | K10: =J10*1.08
A11: Other Liabilities | G11: =F11*1.06 | H11: =G11*1.06 | I11: =H11*1.06 | J11: =I11*1.06 | K11: =J11*1.06
A12: Total Liabilities | B12: 1580830 | C12: 1799507 | D12: 2122934 | E12: 2530432 | F12: 4030194 | G12: =G10+G11 | H12: =H10+H11 | I12: =I10+I11 | J12: =J10+J11 | K12: =K10+K11
A14: Fixed Assets | G14: =F14*1.05 | H14: =G14*1.05 | I14: =H14*1.05 | J14: =I14*1.05 | K14: =J14*1.05
A15: Investments | B15: 389305 | C15: 438823 | D15: 449264 | E15: 511582 | F15: 1005682 | G15: =F15*1.10 | H15: =G15*1.10 | I15: =H15*1.10 | J15: =I15*1.10 | K15: =J15*1.10
A16: Advances/Loans | G16: =F16*(1+Assumptions!$B$5/100) | H16: =G16*(1+Assumptions!$C$5/100) | I16: =H16*(1+Assumptions!$D$5/100) | J16: =I16*(1+Assumptions!$E$5/100) | K16: =J16*(1+Assumptions!$F$5/100)
A17: Other Assets | G17: =F17*1.05 | H17: =G17*1.05 | I17: =H17*1.05 | J17: =I17*1.05 | K17: =J17*1.05
A18: Total Assets | B18: 1580830 | C18: 1799507 | D18: 2122934 | E18: 2530432 | F18: 4030194 | G18: =G8+G12 | H18: =H8+H12 | I18: =I8+I12 | J18: =J8+J12 | K18: =K8+K12

Sheet ROE Tree
A1: ROE DECOMPOSITION (DUPONT ANALYSIS)
A2: ROE = Net Profit Margin x Asset Turnover x Equity Multiplier
A4: Metric | B4: Mar 2021 | C4: Mar 2022 | D4: Mar 2023 | E4: Mar 2024 | F4: Mar 2025 | G4: FY26E | H4: FY27E | I4: FY28E | J4: FY29E | K4: FY30E
A6: PROFITABILITY
A7: Net Profit (PAT) | B7: ='P&L'!B19 | C7: ='P&L'!C19 | D7: ='P&L'!D19 | E7: ='P&L'!E19 | F7: ='P&L'!F19 | G7: ='P&L'!G19 | H7: ='P&L'!H19 | I7: ='P&L'!I19 | ... K7: ='P&L'!K19
A8: Revenue | B8: ='P&L'!B5 | C8: ='P&L'!C5 | D8: ='P&L'!D5 | E8: ='P&L'!E5 | F8: ='P&L'!F5 | G8: ='P&L'!G5 | H8: ='P&L'!H5 | I8: ='P&L'!I5 | ... K8: ='P&L'!K5
A9: Net Profit Margin (%) | B9: =IF(B8=0,0,B7/B8*100) | C9: =IF(C8=0,0,C7/C8*100) | D9: =IF(D8=0,0,D7/D8*100) | E9: =IF(E8=0,0,E7/E8*100) | F9: =IF(F8=0,0,F7/F8*100) | G9: =IF(G8=0,0,G7/G8*100) | H9: =IF(H8=0,0,H7/H8*100) | I9: =IF(I8=0,0,I7/I8*100) | ... K9: =IF(K8=0,0,K7/K8*100)
A11: EFFICIENCY
A12: Revenue | B12: ='P&L'!B5 | C12: ='P&L'!C5 | D12: ='P&L'!D5 | E12: ='P&L'!E5 | F12: ='P&L'!F5 | G12: ='P&L'!G5 | H12: ='P&L'!H5 | I12: ='P&L'!I5 | ... K12: ='P&L'!K5
A13: Average Total Assets | B13: ='Balance Sheet'!B18 | C13: =('Balance Sheet'!C18+'Balance Sheet'!B18)/2 | D13: =('Balance Sheet'!D18+'Balance Sheet'!C18)/2 | E13: =('Balance Sheet'!E18+'Balance Sheet'!D18)/2 | F13: =('Balance Sheet'!F18+'Balance Sheet'!E18)/2 | G13: =('Balance Sheet'!G18+'Balance Sheet'!F18)/2 | H13: =('Balance Sheet'!H18+'Balance Sheet'!G18)/2 | I13: =('Balance Sheet'!I18+'Balance Sheet'!H18)/2 | J13: =('Balance Sheet'!J18+'Balance Sheet'!I18)/2 | K13: =('Balance Sheet'!K18+'Balance Sheet'!J18)/2
A14: Asset Turnover (x) | B14: =IF(B13=0,0,B12/B13) | C14: =IF(C13=0,0,C12/C13) | D14: =IF(D13=0,0,D12/D13) | E14: =IF(E13=0,0,E12/E13) | F14: =IF(F13=0,0,F12/F13) | G14: =IF(G13=0,0,G12/G13) | H14: =IF(H13=0,0,H12/H13) | I14: =IF(I13=0,0,I12/I13) | ... K14: =IF(K13=0,0,K12/K13)
A16: LEVERAGE
A17: Average Total Assets | B17: ='Balance Sheet'!B18 | C17: =('Balance Sheet'!C18+'Balance Sheet'!B18)/2 | D17: =('Balance Sheet'!D18+'Balance Sheet'!C18)/2 | E17: =('Balance Sheet'!E18+'Balance Sheet'!D18)/2 | F17: =('Balance Sheet'!F18+'Balance Sheet'!E18)/2 | G17: =('Balance Sheet'!G18+'Balance Sheet'!F18)/2 | H17: =('Balance Sheet'!H18+'Balance Sheet'!G18)/2 | I17: =('Balance Sheet'!I18+'Balance Sheet'!H18)/2 | J17: =('Balance Sheet'!J18+'Balance Sheet'!I18)/2 | K17: =('Balance Sheet'!K18+'Balance Sheet'!J18)/2
A18: Average Equity | B18: ='Balance Sheet'!B8 | C18: =('Balance Sheet'!C8+'Balance Sheet'!B8)/2 | D18: =('Balance Sheet'!D8+'Balance Sheet'!C8)/2 | E18: =('Balance Sheet'!E8+'Balance Sheet'!D8)/2 | F18: =('Balance Sheet'!F8+'Balance Sheet'!E8)/2 | G18: =('Balance Sheet'!G8+'Balance Sheet'!F8)/2 | H18: =('Balance Sheet'!H8+'Balance Sheet'!G8)/2 | I18: =('Balance Sheet'!I8+'Balance Sheet'!H8)/2 | J18: =('Balance Sheet'!J8+'Balance Sheet'!I8)/2 | K18: =('Balance Sheet'!K8+'Balance Sheet'!J8)/2
A19: Equity Multiplier (x) | B19: =IF(B18=0,0,B17/B18) | C19: =IF(C18=0,0,C17/C18) | D19: =IF(D18=0,0,D17/D18) | E19: =IF(E18=0,0,E17/E18) | F19: =IF(F18=0,0,F17/F18) | G19: =IF(G18=0,0,G17/G18) | H19: =IF(H18=0,0,H17/H18) | I19: =IF(I18=0,0,I17/I18) | ... K19: =IF(K18=0,0,K17/K18)
A21: ROE CALCULATION
A22: ROE (%) | B22: =IF(B18=0,0,B7/B18*100) | C22: =IF(C18=0,0,C7/C18*100) | D22: =IF(D18=0,0,D7/D18*100) | E22: =IF(E18=0,0,E7/E18*100) | F22: =IF(F18=0,0,F7/F18*100) | G22: =IF(G18=0,0,G7/G18*100) | H22: =IF(H18=0,0,H7/H18*100) | I22: =IF(I18=0,0,I7/I18*100) | ... K22: =IF(K18=0,0,K7/K18*100)
A23: ROE Check: NPM x AT x EM (%) | B23: =B9/100*B14*B19*100 | C23: =C9/100*C14*C19*100 | D23: =D9/100*D14*D19*100 | E23: =E9/100*E14*E19*100 | F23: =F9/100*F14*F19*100 | G23: =G9/100*G14*G19*100 | H23: =H9/100*H14*H19*100 | I23: =I9/100*I14*I19*100 | ... K23: =K9/100*K14*K19*100
A26: INTERPRETATION
A27: ROE = Net Profit Margin x Asset Turnover x Equity Multiplier
A28: - Net Profit Margin: How much profit per rupee of revenue (profitability)
A29: - Asset Turnover: How efficiently assets generate revenue (efficiency)
A30: - Equity Multiplier: Financial leverage (higher = more debt)

Sheet Quarterly
A1: QUARTERLY RESULTS
A3: Line Item | B3: Dec 2023 | C3: Dec 2024 | D3: Dec 2025 | E3: Jun 2023 | F3: Jun 2024 | G3: Jun 2025 | H3: Mar 2023 | I3: Mar 2024 | J3: Mar 2025 | K3: Sep 2023 | L3: Sep 2024 | M3: Sep 2025
A4: Revenue + | B4: 75039 | C4: 83002 | D4: 86994 | E4: 47548 | F4: 79434 | G4: 86779 | H4: 45002 | I4: 78008 | J4: 85040 | K4: 51168 | L4: 81546 | M4: 87372
A5: Interest | B5: 41250 | C5: 45414 | D5: 46741 | E5: 22606 | F5: 43692 | G5: 46986 | H5: 20505 | I5: 43242 | J5: 46914 | K5: 25955 | L5: 44580 | M5: 47709
A6: Expenses + | B6: 45349 | C6: 52074 | D6: 45161 | E6: 17770 | F6: 62938 | G6: 47709 | H6: 16682 | I6: 50530 | J6: 41307 | K6: 18470 | L6: 49690 | M6: 64497
A7: Financing Profit | B7: -11560 | C7: -14487 | D7: -4908 | E7: 7172 | F7: -27196 | G7: -7916 | H7: 7815 | I7: -15764 | J7: -3181 | K7: 6744 | L7: -12723 | M7: -24833
A8: Financing Margin % | B8: -15 | C8: -17 | D8: -6 | E8: 15 | F8: -34 | G8: -9 | H8: 17 | I8: -20 | J8: -4 | K8: 13 | L8: -16 | M8: -28
A9: Other Income + | B9: 32528 | C9: 38455 | D9: 31567 | E9: 9610 | F9: 44958 | G9: 33489 | H9: 9121 | I9: 37007 | J9: 27154 | K9: 9853 | L9: 35450 | M9: 45683
A10: Depreciation | B10: 0 | C10: 0 | D10: 0 | E10: 0 | F10: 0 | G10: 0 | H10: 0 | I10: 0 | J10: 0 | K10: 0 | L10: 0 | M10: 0
A11: Profit before tax | B11: 20967 | C11: 23968 | D11: 26659 | E11: 16783 | F11: 17761 | G11: 25573 | H11: 16936 | I11: 21243 | J11: 23973 | K11: 16597 | L11: 22727 | M11: 20850
A12: Tax % | B12: 17 | C12: 22 | D12: 24 | E12: 25 | F12: -1 | G12: 25 | H12: 25 | I12: 17 | J12: 24 | K12: 25 | L12: 24 | M12: 18
A13: Net Profit + | B13: 17312 | C13: 18627 | D13: 20364 | E13: 12634 | F13: 18013 | G13: 19285 | H13: 12735 | I13: 17718 | J13: 18340 | K13: 12403 | L13: 17188 | M13: 17090
A14: EPS in Rs | B14: 11.09 | C14: 11.68 | D14: 12.76 | E14: 11.29 | F14: 11.6 | G14: 12.31 | H14: 11.39 | I14: 11.37 | J14: 11.54 | K14: 11.06 | L14: 10.83 | M14: 10.6

Sheet Key Ratios
A1: KEY FINANCIAL RATIOS
A3: Ratio | B3: Mar 2016 | C3: Mar 2017 | D3: Mar 2018 | E3: Mar 2019 | F3: Mar 2020 | G3: Mar 2021 | H3: Mar 2022 | I3: Mar 2023 | J3: Mar 2024 | K3: Mar 2025
A4: ROE % | B4: 20 | C4: 19 | D4: 18 | E4: 18 | F4: 17 | G4: 16 | H4: 16 | I4: 17 | J4: 17 | K4: 17

Sheet Valuation
A1: VALUATION
A3: RESIDUAL INCOME VALUATION (RIV)
A5: Parameter | B5: Value | C5: Formula/Note
A6: Risk-Free Rate (Rf) | B6: 7.0% | C6: 10-year G-Sec yield
A7: Equity Risk Premium | B7: 6.0% | C7: India market premium
A8: Beta | B8: 1.0 | C8: Large-cap bank assumption
A9: Cost of Equity (Ke) | B9: 13.0% | C9: =Rf + Beta*ERP
A10: Terminal Growth (g) | B10: 4.0% | C10: Long-term GDP growth
A12: Current Book Value | B12: Rs.0 | C12: From Screener
A13: Sustainable ROE | B13: 15% | C13: From assumptions
A15: Fair Value per Share | B15: Rs.1,825 | C15: =BV + RI/(Ke-g)
A16: Current Market Price | B16: Rs.1,742.85 | C16: Live price
A17: Target Price | B17: Rs.1,850 | C17: 12-month target
A18: Upside/Downside | B18: 6.1% | C18: =(TP-CMP)/CMP
A21: RECOMMENDATION
A22: HOLD
A24: HDFC Bank's ROE of 16.5% exceeds cost of equity of 13%, generating positive residual income. Fair value indicates modest upside of ~6%, suggesting current valuation is reasonable but not compelling for aggressive buying given the premium banking sector multiples.

Sheet Peer Comparison
A1: PEER COMPARISON
A3: Name
A4: S.No.
A5: 1.
A6: 2.
A7: 3.
A8: 4.
A9: 5.
A10: 6.
A11: 7.

Sheet Thesis
A1: INVESTMENT THESIS
A2: HDFC Bank Ltd (HDFCBANK)
A4: HOLD | Target: Rs.1,850 | Upside: 6.1%
A7: STRENGTHS (from Screener.in)
A8: * Company has delivered good profit growth of 21.0% CAGR over last 5 years
A9: * Company has been maintaining a healthy dividend payout of 23.3%
A10: * Company's median sales growth is 16.4% of last 10 years
A12: RISKS (from Screener.in)
A13: * Stock is trading at 2.50 times its book value
A14: * Company has low interest coverage ratio.
A15: * Contingent liabilities of Rs.27,80,601 Cr.
A16: * Earnings include an other income of Rs.1,50,600 Cr.
... A20: ## HDFC BANK LTD (HDFCBANK) | HOLD | TP: ₹1,850 **RECOMMENDATION SUMMARY** We maintain a HOLD rating on HDFC Bank with a target price of ₹1,850, implying 6.1% upside from current levels. Limited near-term appreciation potential given post-merger integration challenges and valuation at sector premiums. **INVESTMENT CASE** • **Merger integration progressing**: The HDFC Ltd merger has created India's largest private sector bank with expanded balance sheet scale and cross-selling opportunities, though operating efficiency metrics remain under pressure during the transition period • **Strong liability franchise**: Best-in-class CASA ratio among large private banks provides sustainable low-cost funding advantage, critical for maintaining NIMs in a competitive lending environment • **Asset quality resilience**: Credit costs remain contained with GNPA/NNPA ratios below peer averages, supported by robust underwriting standards and diversified loan book across retail, SME, and corporate segments • **Digital transformation**: Continued investments in technology infrastructure and digital banking capabilities position the bank well for market share gains among younger demographics and urban markets **KEY RISKS** • **Margin pressure**: Elevated CD ratio post-merger (approaching 110%) constrains lending growth and pressures margins until deposit mobilization catches up with loan book expansion • **Integration execution risk**: Operational complexities from systems integration, branch rationalization, and cultural alignment could impact service quality and productivity metrics over 12-18 months • **Regulatory overhang**: Heightened RBI scrutiny on large banks regarding digital banking outages, lending practices, and systemic importance requirements may lead to higher compliance costs **VALUATION** Our TP of ₹1,850 is based on 2.8x FY26E P/B, broadly in line with the stock's 5-year average multiple. While HDFC Bank historically commanded premium valuations versus peers, we apply limited multiple expansion given near-term earnings dilution from merger accounting and deposit growth imperatives. The valuation reflects the franchise's long-term quality but acknowledges execution risks and muted 12-month return potential. Current risk-reward favors waiting for a better entry point. --- *Note: For accumulation on dips below ₹1,650*
