Workbook

Sheet Cover
A1: FINANCIAL MODEL
A2: Unknown Company
A3: Ticker: ICICIAMC
A5: Generated: 23 February 2026 08:19
A7: KEY DATA
A8: Sector | B8: Asset Management
A9: Market Cap | B9: Rs.154,041 Cr
A10: Current Price | B10: Rs.3,116.60
A13: RECOMMENDATION
A14: Rating | B14: HOLD
A15: Target Price | B15: Rs.3,400
A16: Upside | B16: 9.1%
A19: INVESTMENT THESIS
A20: ICICI AMC is a high-quality franchise benefiting from India's structural shift toward financial savings and mutual fund penetration. The company operates an asset-light, high-ROE business model with strong competitive moats including brand, distribution access via ICICI Bank, and product innovation capabilities. Trading at ~48x P/E, valuation appears full but justified by superior growth visibility and profitability metrics. Long-term structural tailwinds remain intact despite near-term market volatility.

Sheet Assumptions
A1: FORECAST ASSUMPTIONS
A2: Change yellow cells to update projections. All linked sheets will recalculate.
A4: Assumption | B4: FY26E | C4: FY27E | D4: FY28E | E4: FY29E | F4: FY30E
A7: RATIONALE
A8: Based on historical trends and sector outlook

Sheet P&L
A1: PROFIT & LOSS STATEMENT
A2: (Rs. Crores) | Green cells = Forecast with formulas
A4: Line Item | B4: Mar 2025 | C4: FY26E | D4: FY27E | E4: FY28E | F4: FY29E | G4: FY30E
A5: Interest Earned | B5: 3758 | C5: =B5*1.12 | D5: =C5*1.12 | E5: =D5*1.12 | F5: =E5*1.12 | G5: =F5*1.12
A6: Interest on Advances | B6: 16 | C6: =B6*1.10 | D6: =C6*1.10 | E6: =D6*1.10 | F6: =E6*1.10 | G6: =F6*1.10
A7: Income on Investments | C7: =B7*1.08 | D7: =C7*1.08 | E7: =D7*1.08 | F7: =E7*1.08 | G7: =F7*1.08
A8: Other Income | B8: 3 | C8: =B8*1.08 | D8: =C8*1.08 | E8: =D8*1.08 | F8: =E8*1.08 | G8: =F8*1.08
A9: Commission & Brokerage | C9: =B9*1.10 | D9: =C9*1.10 | E9: =D9*1.10 | F9: =E9*1.10 | G9: =F9*1.10
A10: Profit on Investments | C10: =B10*1.05 | D10: =C10*1.05 | E10: =D10*1.05 | F10: =E10*1.05 | G10: =F10*1.05
A11: Total Income | B11: =B5+B8+B9+B10 | C11: =C5+C8+C9+C10 | D11: =D5+D8+D9+D10 | E11: =E5+E8+E9+E10 | F11: =F5+F8+F9+F10 | G11: =G5+G8+G9+G10
A13: Interest Expended | C13: =B13*1.10 | D13: =C13*1.10 | E13: =D13*1.10 | F13: =E13*1.10 | G13: =F13*1.10
A14: Interest on Deposits | C14: =B14*1.10 | D14: =C14*1.10 | E14: =D14*1.10 | F14: =E14*1.10 | G14: =F14*1.10
A15: Operating Expenses | B15: 981 | C15: =B15*1.10 | D15: =C15*1.10 | E15: =D15*1.10 | F15: =E15*1.10 | G15: =F15*1.10
A16: Employee Cost | C16: =B16*1.08 | D16: =C16*1.08 | E16: =D16*1.08 | F16: =E16*1.08 | G16: =F16*1.08
A17: Depreciation | B17: 66 | C17: =B17*1.05 | D17: =C17*1.05 | E17: =D17*1.05 | F17: =E17*1.05 | G17: =F17*1.05
A18: Other OpEx | C18: =B18*1.08 | D18: =C18*1.08 | E18: =D18*1.08 | F18: =E18*1.08 | G18: =F18*1.08
A19: Total Expenses | B19: =B13+B15 | C19: =C13+C15 | D19: =D13+D15 | E19: =E13+E15 | F19: =F13+F15 | G19: =G13+G15
A21: Provisions & Contingencies | C21: =B21*1.05 | D21: =C21*1.05 | E21: =D21*1.05 | F21: =E21*1.05 | G21: =F21*1.05
A22: Provision for NPA | C22: =B22*0.95 | D22: =C22*0.95 | E22: =D22*0.95 | F22: =E22*0.95 | G22: =F22*0.95
A23: Provision for Tax | C23: =B23*1.10 | D23: =C23*1.10 | E23: =D23*1.10 | F23: =E23*1.10 | G23: =F23*1.10
A24: Operating Profit | B24: 2777 | C24: =C11-C19 | D24: =D11-D19 | E24: =E11-E19 | F24: =F11-F19 | G24: =G11-G19
A25: Profit Before Tax | B25: 2698 | C25: =C24-C21 | D25: =D24-D21 | E25: =E24-E21 | F25: =F24-F21 | G25: =G24-G21
A26: Tax | B26: 24 | C26: =C25*0.25 | D26: =D25*0.25 | E26: =E25*0.25 | F26: =F25*0.25 | G26: =G25*0.25
A27: Net Profit | B27: 2050 | C27: =C25-C26 | D27: =D25-D26 | E27: =E25-E26 | F27: =F25-F26 | G27: =G25-G26
A28: EPS (Rs.) | B28: 1161.18 | C28: =B28*(C27/B27) | D28: =C28*(D27/C27) | E28: =D28*(E27/D27) | F28: =E28*(F27/E27) | G28: =F28*(G27/F27)
A29: Dividend Payout (%) | B29: 0 | C29: =B29 | D29: =C29 | E29: =D29 | F29: =E29 | G29: =F29
A31: Net Profit Growth (%) | C31: =IF(B27=0,0,(C27/B27-1)*100) | D31: =IF(C27=0,0,(D27/C27-1)*100) | E31: =IF(D27=0,0,(E27/D27-1)*100) | F31: =IF(E27=0,0,(F27/E27-1)*100) | G31: =IF(F27=0,0,(G27/F27-1)*100)

Sheet Balance Sheet
A1: BALANCE SHEET
A2: (Rs. Crores) | Green cells = Forecast
A4: Line Item | B4: Mar 2025 | C4: FY26E | D4: FY27E | E4: FY28E | F4: FY29E | G4: FY30E
A5: LIABILITIES
A6: Equity Capital | C6: =B6 | D6: =C6 | E6: =D6 | F6: =E6 | G6: =F6
A7: Reserves | C7: =B7+'P&L'!C27*0.70 | D7: =C7+'P&L'!D27*0.70 | E7: =D7+'P&L'!E27*0.70 | F7: =E7+'P&L'!F27*0.70 | G7: =F7+'P&L'!G27*0.70
A8: Total Equity | B8: =B6+B7 | C8: =C6+C7 | D8: =D6+D7 | E8: =E6+E7 | F8: =F6+F7 | G8: =G6+G7
A10: Deposits | C10: =B10*1.12 | D10: =C10*1.12 | E10: =D10*1.12 | F10: =E10*1.12 | G10: =F10*1.12
A11: CASA Deposits | C11: =B11*1.14 | D11: =C11*1.14 | E11: =D11*1.14 | F11: =E11*1.14 | G11: =F11*1.14
A12: Borrowings | C12: =B12*1.08 | D12: =C12*1.08 | E12: =D12*1.08 | F12: =E12*1.08 | G12: =F12*1.08
A13: Other Liabilities | C13: =B13*1.10 | D13: =C13*1.10 | E13: =D13*1.10 | F13: =E13*1.10 | G13: =F13*1.10
A14: Total Liabilities | C14: =C8+C10+C12+C13 | D14: =D8+D10+D12+D13 | E14: =E8+E10+E12+E13 | F14: =F8+F10+F12+F13 | G14: =G8+G10+G12+G13
A16: ASSETS
A17: Cash & Bank Balances | C17: =B17*1.08 | D17: =C17*1.08 | E17: =D17*1.08 | F17: =E17*1.08 | G17: =F17*1.08
A18: Fixed Assets | C18: =B18*1.05 | D18: =C18*1.05 | E18: =D18*1.05 | F18: =E18*1.05 | G18: =F18*1.05
A19: CWIP | C19: =B19*1.02 | D19: =C19*1.02 | E19: =D19*1.02 | F19: =E19*1.02 | G19: =F19*1.02
A20: Investments | C20: =B20*1.10 | D20: =C20*1.10 | E20: =D20*1.10 | F20: =E20*1.10 | G20: =F20*1.10
A21: Advances | C21: =B21*1.12 | D21: =C21*1.12 | E21: =D21*1.12 | F21: =E21*1.12 | G21: =F21*1.12
A22: Other Assets | C22: =B22*1.08 | D22: =C22*1.08 | E22: =D22*1.08 | F22: =E22*1.08 | G22: =F22*1.08
A23: Total Assets | C23: =C14 | D23: =D14 | E23: =E14 | F23: =F14 | G23: =G14

Sheet ROE Tree
A1: ROE DECOMPOSITION (DUPONT ANALYSIS)
A2: ROE = Net Profit Margin x Asset Turnover x Equity Multiplier
A4: Metric | B4: Mar 2025 | C4: FY26E | D4: FY27E | E4: FY28E | F4: FY29E | G4: FY30E
A6: PROFITABILITY
A7: Net Profit (PAT) | B7: ='P&L'!B27 | C7: ='P&L'!C27 | D7: ='P&L'!D27 | E7: ='P&L'!E27 | F7: ='P&L'!F27 | G7: ='P&L'!G27
A8: Revenue | B8: ='P&L'!B5 | C8: ='P&L'!C5 | D8: ='P&L'!D5 | E8: ='P&L'!E5 | F8: ='P&L'!F5 | G8: ='P&L'!G5
A9: Net Profit Margin (%) | B9: =IF(B8=0,0,B7/B8*100) | C9: =IF(C8=0,0,C7/C8*100) | D9: =IF(D8=0,0,D7/D8*100) | E9: =IF(E8=0,0,E7/E8*100) | F9: =IF(F8=0,0,F7/F8*100) | G9: =IF(G8=0,0,G7/G8*100)
A11: EFFICIENCY
A12: Revenue | B12: ='P&L'!B5 | C12: ='P&L'!C5 | D12: ='P&L'!D5 | E12: ='P&L'!E5 | F12: ='P&L'!F5 | G12: ='P&L'!G5
A13: Average Total Assets | B13: ='Balance Sheet'!B23 | C13: =('Balance Sheet'!C23+'Balance Sheet'!B23)/2 | D13: =('Balance Sheet'!D23+'Balance Sheet'!C23)/2 | E13: =('Balance Sheet'!E23+'Balance Sheet'!D23)/2 | F13: =('Balance Sheet'!F23+'Balance Sheet'!E23)/2 | G13: =('Balance Sheet'!G23+'Balance Sheet'!F23)/2
A14: Asset Turnover (x) | B14: =IF(B13=0,0,B12/B13) | C14: =IF(C13=0,0,C12/C13) | D14: =IF(D13=0,0,D12/D13) | E14: =IF(E13=0,0,E12/E13) | F14: =IF(F13=0,0,F12/F13) | G14: =IF(G13=0,0,G12/G13)
A16: LEVERAGE
A17: Average Total Assets | B17: ='Balance Sheet'!B23 | C17: =('Balance Sheet'!C23+'Balance Sheet'!B23)/2 | D17: =('Balance Sheet'!D23+'Balance Sheet'!C23)/2 | E17: =('Balance Sheet'!E23+'Balance Sheet'!D23)/2 | F17: =('Balance Sheet'!F23+'Balance Sheet'!E23)/2 | G17: =('Balance Sheet'!G23+'Balance Sheet'!F23)/2
A18: Average Equity | B18: ='Balance Sheet'!B8 | C18: =('Balance Sheet'!C8+'Balance Sheet'!B8)/2 | D18: =('Balance Sheet'!D8+'Balance Sheet'!C8)/2 | E18: =('Balance Sheet'!E8+'Balance Sheet'!D8)/2 | F18: =('Balance Sheet'!F8+'Balance Sheet'!E8)/2 | G18: =('Balance Sheet'!G8+'Balance Sheet'!F8)/2
A19: Equity Multiplier (x) | B19: =IF(B18=0,0,B17/B18) | C19: =IF(C18=0,0,C17/C18) | D19: =IF(D18=0,0,D17/D18) | E19: =IF(E18=0,0,E17/E18) | F19: =IF(F18=0,0,F17/F18) | G19: =IF(G18=0,0,G17/G18)
A21: ROE CALCULATION
A22: ROE (%) | B22: =IF(B18=0,0,B7/B18*100) | C22: =IF(C18=0,0,C7/C18*100) | D22: =IF(D18=0,0,D7/D18*100) | E22: =IF(E18=0,0,E7/E18*100) | F22: =IF(F18=0,0,F7/F18*100) | G22: =IF(G18=0,0,G7/G18*100)
A23: ROE Check: NPM x AT x EM (%) | B23: =B9/100*B14*B19*100 | C23: =C9/100*C14*C19*100 | D23: =D9/100*D14*D19*100 | E23: =E9/100*E14*E19*100 | F23: =F9/100*F14*F19*100 | G23: =G9/100*G14*G19*100
A26: INTERPRETATION
A27: ROE = Net Profit Margin x Asset Turnover x Equity Multiplier
A28: - Net Profit Margin: How much profit per rupee of revenue (profitability)
A29: - Asset Turnover: How efficiently assets generate revenue (efficiency)
A30: - Equity Multiplier: Financial leverage (higher = more debt)

Sheet Quarterly
A1: QUARTERLY RESULTS
A3: Line Item

Sheet Key Ratios
A1: KEY FINANCIAL RATIOS
A3: Ratio | B3: Mar 2025

Sheet Valuation
A1: VALUATION MODEL
A2: Residual Income Valuation (RIV) - All values linked to projected financials
A4: VALUATION INPUTS
A6: Parameter | B6: Value | C6: Note
A7: Risk-Free Rate (Rf) | B7: 0.07 | C7: 10-year G-Sec yield
A8: Equity Risk Premium | B8: 0.06 | C8: India market premium
A9: Beta | B9: 1 | C9: Company beta
A10: Cost of Equity (Ke) | B10: =B7+B9*B8 | C10: =Rf + Beta × ERP
A11: Terminal Growth (g) | B11: 0.04 | C11: Long-term GDP growth
A12: Shares Outstanding (Cr) | B12: 1538
A14: PROJECTED FINANCIALS
A16: Metric | B16: FY26E | C16: FY27E | D16: FY28E | E16: FY29E | F16: FY30E
A17: Net Profit (Rs. Cr) | B17: ='P&L'!C27 | C17: ='P&L'!D27 | D17: ='P&L'!E27 | E17: ='P&L'!F27 | F17: ='P&L'!G27
A18: Shareholders' Equity (Rs. Cr) | B18: ='Balance Sheet'!C8 | C18: ='Balance Sheet'!D8 | D18: ='Balance Sheet'!E8 | E18: ='Balance Sheet'!F8 | F18: ='Balance Sheet'!G8
A19: Opening Equity (Rs. Cr) | B19: ='Balance Sheet'!B8 | C19: =B18 | D19: =C18 | E19: =D18 | F19: =E18
A20: Average Equity (Rs. Cr) | B20: =(B18+B19)/2 | C20: =(C18+C19)/2 | D20: =(D18+D19)/2 | E20: =(E18+E19)/2 | F20: =(F18+F19)/2
A21: ROE (%) | B21: =IF(B20=0,0,B17/B20) | C21: =IF(C20=0,0,C17/C20) | D21: =IF(D20=0,0,D17/D20) | E21: =IF(E20=0,0,E17/E20) | F21: =IF(F20=0,0,F17/F20)
A23: RESIDUAL INCOME CALCULATION
A25: Component | B25: FY26E | C25: FY27E | D25: FY28E | E25: FY29E | F25: FY30E
A26: Required Return (Rs. Cr) | B26: =B19*$B$10 | C26: =C19*$B$10 | D26: =D19*$B$10 | E26: =E19*$B$10 | F26: =F19*$B$10
A27: Residual Income (Rs. Cr) | B27: =B17-B26 | C27: =C17-C26 | D27: =D17-D26 | E27: =E17-E26 | F27: =F17-F26
A28: Discount Factor | B28: =1/(1+$B$10)^1 | C28: =1/(1+$B$10)^2 | D28: =1/(1+$B$10)^3 | E28: =1/(1+$B$10)^4 | F28: =1/(1+$B$10)^5
A29: PV of Residual Income (Rs. Cr) | B29: =B27*B28 | C29: =C27*C28 | D29: =D27*D28 | E29: =E27*E28 | F29: =F27*F28
A31: VALUATION SUMMARY
A33: Current Book Value (Rs. Cr) | B33: ='Balance Sheet'!B8
A34: Sum of PV of RI (Rs. Cr) | B34: =B29+C29+D29+E29+F29
A35: Terminal Value (Rs. Cr) | B35: =F27*(1+$B$11)/($B$10-$B$11)*F28
A36: Total Equity Value (Rs. Cr) | B36: =B33+B34+B35
A38: PER SHARE VALUATION
A40: Fair Value per Share (Rs.) | B40: =B36/B12
A41: Current Market Price (Rs.) | B41: 3116.6
A42: Upside / Downside (%) | B42: =(B40-B41)/B41
A44: RECOMMENDATION
A45: HOLD
A47: Based on RIV valuation model

Sheet Peer Comparison
A1: PEER COMPARISON
A3: No peer data available

Sheet Thesis
A1: INVESTMENT THESIS
A2: Company (ICICIAMC)
A4: HOLD | Target: Rs.3,400 | Upside: 9.1%
A7: STRENGTHS (from Screener.in)
A9: RISKS (from Screener.in)
A12: DETAILED ANALYSIS
A13: See valuation and assumptions sheets for details.
