Workbook

Sheet Cover
A1: FINANCIAL MODEL
A2: Unknown Company
A3: Ticker: SBIN
A5: Generated: 24 February 2026 15:05
A7: KEY DATA
A8: Sector | B8: Banking
A9: Market Cap | B9: Rs.0 Cr
A10: Current Price | B10: Rs.1,216.10
A13: RECOMMENDATION
A14: Rating | B14: SELL / REDUCE
A15: Target Price | B15: Rs.950
A16: Upside | B16: -21.9%
A19: INVESTMENT THESIS
A20: State Bank of India is India's largest and best-performing PSU bank with significantly improved fundamentals - ROE of 17-18%, GNPA <2.5%, and strong CASA franchise at 43-45%. However, at 1.9x P/B and 13.2x P/E, the stock is trading at a premium valuation that is not justified even for a best-in-class PSU bank. Fair valuation using RIV model suggests 1.5x P/B or ₹962, implying 22% downside from current levels. While the operational performance is commendable, valuation has run ahead of fundamentals.

Sheet P&L
A1: PROFIT & LOSS STATEMENT
A2: (Rs. Crores) | Green cells = Forecast with formulas
A4: Line Item | B4: Mar 2022 | C4: Mar 2023 | D4: Mar 2024 | E4: Mar 2025 | F4: FY26E | G4: FY27E | H4: FY28E | I4: FY29E | J4: FY30E
A5: Interest Earned | B5: 278115 | C5: 289973 | D5: 350845 | E5: 439189 | F5: =E5*1.12 | G5: =F5*1.12 | H5: =G5*1.12 | I5: =H5*1.12 | J5: =I5*1.12
A6: Interest on Advances | B6: 156010 | C6: 156194 | D6: 189981 | E6: 259736 | F6: =E6*1.10 | G6: =F6*1.10 | H6: =G6*1.10 | I6: =H6*1.10 | J6: =I6*1.10
A7: Income on Investments | F7: =E7*1.08 | G7: =F7*1.08 | H7: =G7*1.08 | I7: =H7*1.08 | J7: =I7*1.08
A8: Other Income | B8: 107222 | C8: 117000 | D8: 122534 | E8: 155386 | F8: =E8*1.08 | G8: =F8*1.08 | H8: =G8*1.08 | I8: =H8*1.08 | J8: =I8*1.08
A9: Commission & Brokerage | F9: =E9*1.10 | G9: =F9*1.10 | H9: =G9*1.10 | I9: =H9*1.10 | J9: =I9*1.10
A10: Profit on Investments | F10: =E10*1.05 | G10: =F10*1.05 | H10: =G10*1.05 | I10: =H10*1.05 | J10: =I10*1.05
A11: Total Income | B11: =B5+B8+B9+B10 | C11: =C5+C8+C9+C10 | D11: =D5+D8+D9+D10 | E11: =E5+E8+E9+E10 | F11: =F5+F8+F9+F10 | G11: =G5+G8+G9+G10 | H11: =H5+H8+H9+H10 | I11: =I5+I8+I9+I10 | J11: =J5+J8+J9+J10
A13: Interest Expended | F13: =E13*1.10 | G13: =F13*1.10 | H13: =G13*1.10 | I13: =H13*1.10 | J13: =I13*1.10
A14: Interest on Deposits | F14: =E14*1.10 | G14: =F14*1.10 | H14: =G14*1.10 | I14: =H14*1.10 | J14: =I14*1.10
A15: Operating Expenses | B15: 192821 | C15: 197349 | D15: 204303 | E15: 239750 | F15: =E15*1.10 | G15: =F15*1.10 | H15: =G15*1.10 | I15: =H15*1.10 | J15: =I15*1.10
A16: Employee Cost | F16: =E16*1.08 | G16: =F16*1.08 | H16: =G16*1.08 | I16: =H16*1.08 | J16: =I16*1.08
A17: Depreciation | B17: 3711 | C17: 3691 | D17: 3696 | E17: 3849 | F17: =E17*1.05 | G17: =F17*1.05 | H17: =G17*1.05 | I17: =H17*1.05 | J17: =I17*1.05
A18: Other OpEx | F18: =E18*1.08 | G18: =F18*1.08 | H18: =G18*1.08 | I18: =H18*1.08 | J18: =I18*1.08
A19: Total Expenses | B19: =B13+B15 | C19: =C13+C15 | D19: =D13+D15 | E19: =E13+E15 | F19: =F13+F15 | G19: =G13+G15 | H19: =H13+H15 | I19: =I13+I15 | J19: =J13+J15
A21: Provisions & Contingencies | F21: =E21*1.05 | G21: =F21*1.05 | H21: =G21*1.05 | I21: =H21*1.05 | J21: =I21*1.05
A22: Provision for NPA | F22: =E22*0.95 | G22: =F22*0.95 | H22: =G22*0.95 | I22: =H22*0.95 | J22: =I22*0.95
A23: Provision for Tax | F23: =E23*1.10 | G23: =F23*1.10 | H23: =G23*1.10 | I23: =H23*1.10 | J23: =I23*1.10
A24: Operating Profit | F24: =F11-F19 | G24: =G11-G19 | H24: =H11-H19 | I24: =I11-I19 | J24: =J11-J19
A25: Profit Before Tax | B25: 32796 | C25: 49739 | D25: 75399 | E25: 91240 | F25: =F24-F21 | G25: =G24-G21 | H25: =H24-H21 | I25: =I24-I21 | J25: =J24-J21
A26: Tax | B26: 26 | C26: 27 | D26: 25 | E26: 25 | F26: =F25*0.25 | G26: =G25*0.25 | H26: =H25*0.25 | I26: =I25*0.25 | J26: =J25*0.25
A27: Net Profit | B27: 23888 | C27: 37183 | D27: 57750 | E27: 69543 | F27: =F25-F26 | G27: =G25-G26 | H27: =H25-H26 | I27: =I25-I26 | J27: =J25-J26
A28: EPS (Rs.) | B28: 25.11 | C28: 39.64 | D28: 62.35 | E28: 75.17 | F28: =E28*(F27/E27) | G28: =F28*(G27/F27) | H28: =G28*(H27/G27) | I28: =H28*(I27/H27) | J28: =I28*(J27/I27)
A29: Dividend Payout (%) | B29: 16 | C29: 18 | D29: 18 | E29: 18 | F29: =E29 | G29: =F29 | H29: =G29 | I29: =H29 | J29: =I29
A31: Net Profit Growth (%) | C31: =IF(B27=0,0,(C27/B27-1)*100) | D31: =IF(C27=0,0,(D27/C27-1)*100) | E31: =IF(D27=0,0,(E27/D27-1)*100) | F31: =IF(E27=0,0,(F27/E27-1)*100) | G31: =IF(F27=0,0,(G27/F27-1)*100) | H31: =IF(G27=0,0,(H27/G27-1)*100) | I31: =IF(H27=0,0,(I27/H27-1)*100) | J31: =IF(I27=0,0,(J27/I27-1)*100)

Sheet Balance Sheet
A1: BALANCE SHEET
A2: (Rs. Crores) | Green cells = Forecast
A4: Line Item | B4: Mar 2022 | C4: Mar 2023 | D4: Mar 2024 | E4: Mar 2025 | F4: FY26E | G4: FY27E | H4: FY28E | I4: FY29E | J4: FY30E
A5: LIABILITIES
A6: Equity Capital | B6: 892 | C6: 892 | D6: 892 | E6: 892 | F6: =E6 | G6: =F6 | H6: =G6 | I6: =H6 | J6: =I6
A7: Reserves | B7: 274669 | C7: 304696 | D7: 358039 | E7: 414047 | F7: =E7+'P&L'!F27*0.70 | G7: =F7+'P&L'!G27*0.70 | H7: =G7+'P&L'!H27*0.70 | I7: =H7+'P&L'!I27*0.70 | J7: =I7+'P&L'!J27*0.70
A8: Total Equity | B8: =B6+B7 | C8: =C6+C7 | D8: =D6+D7 | E8: =E6+E7 | F8: =F6+F7 | G8: =G6+G7 | H8: =H6+H7 | I8: =I6+I7 | J8: =J6+J7
A10: Deposits | B10: 3715331 | C10: 4087411 | D10: 4468536 | E10: 4966537 | F10: =E10*1.12 | G10: =F10*1.12 | H10: =G10*1.12 | I10: =H10*1.12 | J10: =I10*1.12
A11: CASA Deposits | F11: =E11*1.14 | G11: =F11*1.14 | H11: =G11*1.14 | I11: =H11*1.14 | J11: =I11*1.14
A12: Borrowings | B12: 433796 | C12: 449160 | D12: 521152 | E12: 639610 | F12: =E12*1.08 | G12: =F12*1.08 | H12: =G12*1.08 | I12: =H12*1.08 | J12: =I12*1.08
A13: Other Liabilities | B13: 420926 | C13: 518719 | D13: 605796 | E13: 712669 | F13: =E13*1.10 | G13: =F13*1.10 | H13: =G13*1.10 | I13: =H13*1.10 | J13: =I13*1.10
A14: Total Liabilities | B14: 4845615 | C14: 5360878 | D14: 5954415 | E14: 6733756 | F14: =F8+F10+F12+F13 | G14: =G8+G10+G12+G13 | H14: =H8+H10+H12+H13 | I14: =I8+I10+I12+I13 | J14: =J8+J10+J12+J13
A16: ASSETS
A17: Cash & Bank Balances | F17: =E17*1.08 | G17: =F17*1.08 | H17: =G17*1.08 | I17: =H17*1.08 | J17: =I17*1.08
A18: Fixed Assets | B18: 41600 | C18: 41032 | D18: 45880 | E18: 46072 | F18: =E18*1.05 | G18: =F18*1.05 | H18: =G18*1.05 | I18: =H18*1.05 | J18: =I18*1.05
A19: CWIP | B19: 116 | C19: 28 | D19: 66 | E19: 42 | F19: =E19*1.02 | G19: =F19*1.02 | H19: =G19*1.02 | I19: =H19*1.02 | J19: =I19*1.02
A20: Investments | B20: 1595100 | C20: 1776490 | D20: 1913108 | E20: 2110548 | F20: =E20*1.10 | G20: =F20*1.10 | H20: =G20*1.10 | I20: =H20*1.10 | J20: =I20*1.10
A21: Advances | F21: =E21*1.12 | G21: =F21*1.12 | H21: =G21*1.12 | I21: =H21*1.12 | J21: =I21*1.12
A22: Other Assets | B22: 3208798 | C22: 3543328 | D22: 3995361 | E22: 4577093 | F22: =E22*1.08 | G22: =F22*1.08 | H22: =G22*1.08 | I22: =H22*1.08 | J22: =I22*1.08
A23: Total Assets | B23: 4845615 | C23: 5360878 | D23: 5954415 | E23: 6733756 | F23: =F14 | G23: =G14 | H23: =H14 | I23: =I14 | J23: =J14

Sheet ROE Tree
A1: ROE DECOMPOSITION (DUPONT ANALYSIS)
A2: ROE = Net Profit Margin x Asset Turnover x Equity Multiplier
A4: Metric | B4: Mar 2022 | C4: Mar 2023 | D4: Mar 2024 | E4: Mar 2025 | F4: FY26E | G4: FY27E | H4: FY28E | I4: FY29E | J4: FY30E
A6: PROFITABILITY
A7: Net Profit (PAT) | B7: ='P&L'!B27 | C7: ='P&L'!C27 | D7: ='P&L'!D27 | E7: ='P&L'!E27 | F7: ='P&L'!F27 | G7: ='P&L'!G27 | H7: ='P&L'!H27 | I7: ='P&L'!I27 | J7: ='P&L'!J27
A8: Revenue | B8: ='P&L'!B5 | C8: ='P&L'!C5 | D8: ='P&L'!D5 | E8: ='P&L'!E5 | F8: ='P&L'!F5 | G8: ='P&L'!G5 | H8: ='P&L'!H5 | I8: ='P&L'!I5 | J8: ='P&L'!J5
A9: Net Profit Margin (%) | B9: =IF(B8=0,0,B7/B8*100) | C9: =IF(C8=0,0,C7/C8*100) | D9: =IF(D8=0,0,D7/D8*100) | E9: =IF(E8=0,0,E7/E8*100) | F9: =IF(F8=0,0,F7/F8*100) | G9: =IF(G8=0,0,G7/G8*100) | H9: =IF(H8=0,0,H7/H8*100) | I9: =IF(I8=0,0,I7/I8*100) | J9: =IF(J8=0,0,J7/J8*100)
A11: EFFICIENCY
A12: Revenue | B12: ='P&L'!B5 | C12: ='P&L'!C5 | D12: ='P&L'!D5 | E12: ='P&L'!E5 | F12: ='P&L'!F5 | G12: ='P&L'!G5 | H12: ='P&L'!H5 | I12: ='P&L'!I5 | J12: ='P&L'!J5
A13: Average Total Assets | B13: ='Balance Sheet'!B23 | C13: =('Balance Sheet'!C23+'Balance Sheet'!B23)/2 | D13: =('Balance Sheet'!D23+'Balance Sheet'!C23)/2 | E13: =('Balance Sheet'!E23+'Balance Sheet'!D23)/2 | F13: =('Balance Sheet'!F23+'Balance Sheet'!E23)/2 | G13: =('Balance Sheet'!G23+'Balance Sheet'!F23)/2 | H13: =('Balance Sheet'!H23+'Balance Sheet'!G23)/2 | I13: =('Balance Sheet'!I23+'Balance Sheet'!H23)/2 | J13: =('Balance Sheet'!J23+'Balance Sheet'!I23)/2
A14: Asset Turnover (x) | B14: =IF(B13=0,0,B12/B13) | C14: =IF(C13=0,0,C12/C13) | D14: =IF(D13=0,0,D12/D13) | E14: =IF(E13=0,0,E12/E13) | F14: =IF(F13=0,0,F12/F13) | G14: =IF(G13=0,0,G12/G13) | H14: =IF(H13=0,0,H12/H13) | I14: =IF(I13=0,0,I12/I13) | J14: =IF(J13=0,0,J12/J13)
A16: LEVERAGE
A17: Average Total Assets | B17: ='Balance Sheet'!B23 | C17: =('Balance Sheet'!C23+'Balance Sheet'!B23)/2 | D17: =('Balance Sheet'!D23+'Balance Sheet'!C23)/2 | E17: =('Balance Sheet'!E23+'Balance Sheet'!D23)/2 | F17: =('Balance Sheet'!F23+'Balance Sheet'!E23)/2 | G17: =('Balance Sheet'!G23+'Balance Sheet'!F23)/2 | H17: =('Balance Sheet'!H23+'Balance Sheet'!G23)/2 | I17: =('Balance Sheet'!I23+'Balance Sheet'!H23)/2 | J17: =('Balance Sheet'!J23+'Balance Sheet'!I23)/2
A18: Average Equity | B18: ='Balance Sheet'!B8 | C18: =('Balance Sheet'!C8+'Balance Sheet'!B8)/2 | D18: =('Balance Sheet'!D8+'Balance Sheet'!C8)/2 | E18: =('Balance Sheet'!E8+'Balance Sheet'!D8)/2 | F18: =('Balance Sheet'!F8+'Balance Sheet'!E8)/2 | G18: =('Balance Sheet'!G8+'Balance Sheet'!F8)/2 | H18: =('Balance Sheet'!H8+'Balance Sheet'!G8)/2 | I18: =('Balance Sheet'!I8+'Balance Sheet'!H8)/2 | J18: =('Balance Sheet'!J8+'Balance Sheet'!I8)/2
A19: Equity Multiplier (x) | B19: =IF(B18=0,0,B17/B18) | C19: =IF(C18=0,0,C17/C18) | D19: =IF(D18=0,0,D17/D18) | E19: =IF(E18=0,0,E17/E18) | F19: =IF(F18=0,0,F17/F18) | G19: =IF(G18=0,0,G17/G18) | H19: =IF(H18=0,0,H17/H18) | I19: =IF(I18=0,0,I17/I18) | J19: =IF(J18=0,0,J17/J18)
A21: ROE CALCULATION
A22: ROE (%) | B22: =IF(B18=0,0,B7/B18*100) | C22: =IF(C18=0,0,C7/C18*100) | D22: =IF(D18=0,0,D7/D18*100) | E22: =IF(E18=0,0,E7/E18*100) | F22: =IF(F18=0,0,F7/F18*100) | G22: =IF(G18=0,0,G7/G18*100) | H22: =IF(H18=0,0,H7/H18*100) | I22: =IF(I18=0,0,I7/I18*100) | J22: =IF(J18=0,0,J7/J18*100)
A23: ROE Check: NPM x AT x EM (%) | B23: =B9/100*B14*B19*100 | C23: =C9/100*C14*C19*100 | D23: =D9/100*D14*D19*100 | E23: =E9/100*E14*E19*100 | F23: =F9/100*F14*F19*100 | G23: =G9/100*G14*G19*100 | H23: =H9/100*H14*H19*100 | I23: =I9/100*I14*I19*100 | J23: =J9/100*J14*J19*100
A26: INTERPRETATION
A27: ROE = Net Profit Margin x Asset Turnover x Equity Multiplier
A28: - Net Profit Margin: How much profit per rupee of revenue (profitability)
A29: - Asset Turnover: How efficiently assets generate revenue (efficiency)
A30: - Equity Multiplier: Financial leverage (higher = more debt)

Sheet Quarterly
A1: QUARTERLY RESULTS
A3: Line Item

Sheet Key Ratios
A1: KEY FINANCIAL RATIOS
A3: Ratio | B3: Mar 2021 | C3: Mar 2022 | D3: Mar 2023 | E3: Mar 2024 | F3: Mar 2025
A4: ROE % | B4: 7 | C4: 9 | D4: 12 | E4: 17 | F4: 17

Sheet Valuation
A1: VALUATION MODEL
A2: Residual Income Valuation (RIV) - All values linked to projected financials
A4: VALUATION INPUTS
A6: Parameter | B6: Value | C6: Note
A7: Risk-Free Rate (Rf) | B7: 0.07 | C7: 10-year G-Sec yield
A8: Equity Risk Premium | B8: 0.06 | C8: India market premium
A9: Beta | B9: 1 | C9: Company beta
A10: Cost of Equity (Ke) | B10: =B7+B9*B8 | C10: =Rf + Beta × ERP
A11: Terminal Growth (g) | B11: 0.04 | C11: Long-term GDP growth
A12: Shares Outstanding (Cr) | B12: 1538
A14: PROJECTED FINANCIALS
A16: Metric | B16: FY26E | C16: FY27E | D16: FY28E | E16: FY29E | F16: FY30E
A17: Net Profit (Rs. Cr) | B17: ='P&L'!F27 | C17: ='P&L'!G27 | D17: ='P&L'!H27 | E17: ='P&L'!I27 | F17: ='P&L'!J27
A18: Shareholders' Equity (Rs. Cr) | B18: ='Balance Sheet'!F8 | C18: ='Balance Sheet'!G8 | D18: ='Balance Sheet'!H8 | E18: ='Balance Sheet'!I8 | F18: ='Balance Sheet'!J8
A19: Opening Equity (Rs. Cr) | B19: ='Balance Sheet'!E8 | C19: =B18 | D19: =C18 | E19: =D18 | F19: =E18
A20: Average Equity (Rs. Cr) | B20: =(B18+B19)/2 | C20: =(C18+C19)/2 | D20: =(D18+D19)/2 | E20: =(E18+E19)/2 | F20: =(F18+F19)/2
A21: ROE (%) | B21: =IF(B20=0,0,B17/B20) | C21: =IF(C20=0,0,C17/C20) | D21: =IF(D20=0,0,D17/D20) | E21: =IF(E20=0,0,E17/E20) | F21: =IF(F20=0,0,F17/F20)
A23: RESIDUAL INCOME CALCULATION
A25: Component | B25: FY26E | C25: FY27E | D25: FY28E | E25: FY29E | F25: FY30E
A26: Required Return (Rs. Cr) | B26: =B19*$B$10 | C26: =C19*$B$10 | D26: =D19*$B$10 | E26: =E19*$B$10 | F26: =F19*$B$10
A27: Residual Income (Rs. Cr) | B27: =B17-B26 | C27: =C17-C26 | D27: =D17-D26 | E27: =E17-E26 | F27: =F17-F26
A28: Discount Factor | B28: =1/(1+$B$10)^1 | C28: =1/(1+$B$10)^2 | D28: =1/(1+$B$10)^3 | E28: =1/(1+$B$10)^4 | F28: =1/(1+$B$10)^5
A29: PV of Residual Income (Rs. Cr) | B29: =B27*B28 | C29: =C27*C28 | D29: =D27*D28 | E29: =E27*E28 | F29: =F27*F28
A31: VALUATION SUMMARY
A33: Current Book Value (Rs. Cr) | B33: ='Balance Sheet'!E8
A34: Sum of PV of RI (Rs. Cr) | B34: =B29+C29+D29+E29+F29
A35: Terminal Value (Rs. Cr) | B35: =F27*(1+$B$11)/($B$10-$B$11)*F28
A36: Total Equity Value (Rs. Cr) | B36: =B33+B34+B35
A38: PER SHARE VALUATION
A40: Fair Value per Share (Rs.) | B40: =B36/B12
A41: Current Market Price (Rs.) | B41: 1216.1
A42: Upside / Downside (%) | B42: =(B40-B41)/B41
A44: RECOMMENDATION
A45: SELL / REDUCE
A47: SBI is trading at 1.9x P/B (₹1,216) vs fair value of 1.5x P/B (₹962), implying ~26% overvaluation. While SBI has achieved impressive ROE improvement to 17-18% and best-in-class PSU metrics (GNPA <2.5%, strong CASA 43-45%), the current valuation at 1.9x P/B is stretched for a PSU bank. Even ICICI Bank (superior ROE, NIM, asset quality) trades at 2.87x P/B. SBI's valuation premium has expanded beyond fundamentals. Downside risk of 22% to fair value of ₹950-960. For PSU banks, 1.3-1.6x P/B is reasonable for 16-17% ROE. Recommend REDUCE/SELL with target ₹950.

Sheet Thesis
A1: INVESTMENT THESIS
A2: Company (SBIN)
A4: SELL / REDUCE | Target: Rs.950 | Upside: -21.9%
A7: STRENGTHS (from Screener.in)
A9: RISKS (from Screener.in)
A12: DETAILED ANALYSIS
A13: See valuation and assumptions sheets for details.
